Workbook

Sheet Leyenda
A1: ND SALES v2 – Matriz de trazabilidad y casos de prueba
A2: Equipo MarketGenAI, módulo Ventas (Duoc UC) · Versión 1.14 · 22-10-2026
A4: Qué es | B4: Complemento del Plan de Pruebas. Relaciona cada requerimiento del Consolidado v0.3 con sus casos de prueba, el código donde se verificó y los riesgos del registro del PMBOK v2.
A5: Hojas | B5: Trazabilidad: un renglón por requerimiento, con cantidad de casos y avance (se calcula solo). · Casos de prueba: detalle de cada caso. · Resumen: totales por resultado, prioridad y tipo. · Hitos: qué se prueba en cada hito y su criterio de salida.
A6: Qué completar | B6: Solo las celdas con fondo amarillo claro de la hoja «Casos de prueba»: Resultado, Fecha de ejecución, N° de defecto y Observaciones. El resto de las hojas se actualiza con fórmulas.
A7: Resultado | B7: Pendiente (valor inicial) · Aprobado · Fallido · Bloqueado.
A8: Origen de los casos | B8: Cada caso sale de un criterio de la columna «Se da por cumplido cuando» del Consolidado (criterios validados el 16-10-2026). Los casos negativos y de límite son propuesta de QA para cubrir cada criterio; no agregan requerimientos nuevos.
A9: Prioridad de prueba | B9: Combina la prioridad del Consolidado con el riesgo del PMBOK (R-01 a R-13). Alta: se prueba primero y con más profundidad.
A10: Nivel | B10: Unitaria · Integración · Sistema · E2E · Aceptación.
A11: Automatizable | B11: Sí: se puede cubrir con Pytest. Parcial: parte automática y parte manual. No: se ejecuta manualmente en staging.
A12: Supuestos | B12: 1) Las transiciones entre estados de RF-VTA-05 no están definidas en el Consolidado: son decisión del equipo y deben acordarse con Alloxentric (propuesta en el Anexo B del Plan de Pruebas). 2) La muestra mínima de 20 generaciones para el P90 (RNF-VTA-03) es propuesta de QA. 3) Los casos con CRM, fuentes de vacantes y condiciones comerciales dependen de cuentas e insumos que debe entregar el cliente. 4) El caso «marcar Firmada sin documento» es una interpretación del criterio de RF-VTA-06. 5) Los 60 s del tiempo de generación son una hipótesis de trabajo hasta la medición del 24-10.
A13: Fuera de alcance | B13: RF-VTA-15, RF-VTA-17 y RNF-VTA-07 (diferidos). RF-VTA-06 se prueba solo en su parte de marcar Firmada con documento.
A14: Cambios v1.1 | B14: Cambios v1.1: se precisaron resultados esperados ambiguos y se agregaron casos de seguridad, CRM, autenticación y worker. Integración de pruebas ya realizadas: las 27 pruebas de aceptación de RF-VTA-01 (ID RF01-PA-nn; 21 automatizadas se registran como aprobadas según la suite en verde de esos documentos, 6 manuales o mixtas quedan pendientes) y los 37 casos de RF-VTA-08 (ID RF08-CP-nn, todos aprobados), con sus 7 defectos en la hoja Defectos. Se retiraron CP-001, 002, 003, 005, 035, 036, 085, 086 y 087 por estar cubiertos por esas pruebas. CP-080, 081 y 083 son controles de proceso. Las fórmulas llegan a la fila 300. Se agregaron 82 casos (CP-102 a CP-183) para los requerimientos que no tenían pruebas ya realizadas: casos límite, negativos, de seguridad, de resiliencia y de rendimiento. Los marcados «Posible evidencia» tienen un archivo de pruebas del repositorio por revisar.
A15: Ejemplo de celda a completar | B15: Resultado = Aprobado · Fecha = 2026-10-24 · Defecto = (vacío) · Observaciones = Probado en staging
... A26: Cambios v1.14 | B26: Integración de los resultados del plan propio de RF-VTA-01 (ejecución real del 20-10): RF01-PA-01, 09, 16, 17, 21 y 22 pasan de Pendiente a Aprobado, con su evidencia; siguen pendientes CP-004, CP-100 y CP-101. Se registran los defectos RF01-D-001 y RF01-D-002 (Menores, corregidos). Se corrigen las notas de Trazabilidad de RF-VTA-01, 12 y 13: ya no mencionan defectos abiertos inexistentes (RF12-D-004 y 006, RF13-D-005 y 006). Se unifica la redacción del resultado esperado de CP-017 y CP-018 con la de su seguimiento. No se modificaron otros requerimientos.

Sheet Trazabilidad
A1: Matriz de trazabilidad: requerimiento → código → riesgo → casos de prueba
A2: Las columnas I a M se calculan desde la hoja «Casos de prueba».
A4: ID | B4: Requerimiento | C4: Prioridad Consolidado | D4: Estado actual | E4: En alcance de pruebas | F4: Prioridad de prueba | G4: Riesgos asociados | H4: Código donde se verificó (Anexo A) | I4: N° casos | J4: Aprobados | K4: Fallidos | L4: Pendientes / bloqueados | M4: % aprobado | N4: Observación | O4: Historia de usuario (SRS v2.0) | P4: Diagrama de actividad
A5: RF-VTA-01 | B5: Generación de propuestas comerciales | C5: Alta | D5: Parcial | E5: Sí | F5: Alta | G5: R-02, R-09, R-11 | H5: routers/proposals.py; routers/knowledge.py; services/document_text_service.py; services/rag_proposal_service.py; workers/tasks/proposal_tasks.py | I5: =COUNTIF('Casos de prueba'!$B$5:$B$299,A5) | J5: =COUNTIFS('Casos de prueba'!$B$5:$B$299,A5,'Casos de prueba'!$L$5:$L$299,"Aprobado") | K5: =COUNTIFS('Casos de prueba'!$B$5:$B$299,A5,'Casos de prueba'!$L$5:$L$299,"Fallido") | L5: =I5-J5-K5 | M5: =IF(I5=0,"—",J5/I5) | N5: Integra las 22 pruebas de aceptación de RF-VTA-01 (RF01-PA) y la regresión del plan de RF-VTA-08. Su plan propio (35 casos, ejecución real del 20-10) dio 35 de 35 aprobados; sus resultados se integraron aquí en la rev1.14: RF01-PA-01, 09, 16, 17, 21 y 22 pasan a Aprobado. Defectos RF01-D-001 y RF01-D-002 (Menores), corregidos. Siguen pendientes CP-004, CP-100 y CP-101 (documentos sin relación, límites de la carga y prueba de punta a punta con datos reales de BPO) y la confirmación de NoonDalton de los plazos propuestos (P-6). | O5: HU-01 | P5: 01
A6: RF-VTA-02 | B6: Catálogo de servicios y precios | C6: Alta | D6: No existe | E6: Sí | F6: Alta | G6: R-09 | H6: schemas/proposal.py (líneas de precio) | I6: =COUNTIF('Casos de prueba'!$B$5:$B$299,A6) | J6: =COUNTIFS('Casos de prueba'!$B$5:$B$299,A6,'Casos de prueba'!$L$5:$L$299,"Aprobado") | K6: =COUNTIFS('Casos de prueba'!$B$5:$B$299,A6,'Casos de prueba'!$L$5:$L$299,"Fallido") | L6: =I6-J6-K6 | M6: =IF(I6=0,"—",J6/I6) | O6: HU-02 | P6: 07
A7: RF-VTA-03 | B7: Personalización por perfil de cliente | C7: Alta | D7: No existe | E7: Sí | F7: Alta | G7: — | H7: schemas/customer.py; routers/customers.py | I7: =COUNTIF('Casos de prueba'!$B$5:$B$299,A7) | J7: =COUNTIFS('Casos de prueba'!$B$5:$B$299,A7,'Casos de prueba'!$L$5:$L$299,"Aprobado") | K7: =COUNTIFS('Casos de prueba'!$B$5:$B$299,A7,'Casos de prueba'!$L$5:$L$299,"Fallido") | L7: =I7-J7-K7 | M7: =IF(I7=0,"—",J7/I7) | O7: HU-03 | P7: 03
A8: RF-VTA-04 | B8: Integración con CRM | C8: Alta | D8: Parcial | E8: Sí | F8: Alta | G8: R-08 | H8: routers/proposals.py (send-to-crm); services/crm_service.py; routers/settings.py; frontend api/axios.js, api/proposalsApi.js y views/ContentLibraryPage.jsx (botón «Subir al CRM») | I8: =COUNTIF('Casos de prueba'!$B$5:$B$299,A8) | J8: =COUNTIFS('Casos de prueba'!$B$5:$B$299,A8,'Casos de prueba'!$L$5:$L$299,"Aprobado") | K8: =COUNTIFS('Casos de prueba'!$B$5:$B$299,A8,'Casos de prueba'!$L$5:$L$299,"Fallido") | L8: =I8-J8-K8 | M8: =IF(I8=0,"—",J8/I8) | N8: Ejecución 22-10: de los 13 casos, 13 Aprobados. Primera pasada: 9 Aprobados, 2 Fallidos (CP-019 y CP-115) y 2 Bloqueados por no contar aún con cuentas reales; tras corregir y contar con cuentas de desarrollo, 13 de 13. Defectos RF04-D-001 a RF04-D-008 (3 Mayores y 5 Menores): los 8 Corregidos y reprobados, ninguno abierto. Se probó con un emulador de CRM y, en CP-016, 017, 018, 112 y 116, contra cuentas de desarrollo REALES de HubSpot y Salesforce (cumple «probada con al menos un CRM real» del hito del 14-11). No se probaron las cuentas productivas del cliente. Las correcciones (backend y frontend) están sin commit: falta commit, despliegue y aceptación del cliente. Salvedad: en CP-112 con Salesforce real, 4 de 7 corridas dieron 504 en vez de 401 porque Salesforce tardó más de 8 s (causa externa). Validado funcionalmente, no cerrado. Plan y evidencia: carpeta «RF-VTA-04 Pruebas QA». | O8: HU-04 | P8: 10
A9: RF-VTA-05 | B9: Seguimiento de estado de propuestas | C9: Alta | D9: Parcial | E9: Sí | F9: Alta | G9: R-12 | H9: routers/proposals.py; repositories ProposalsRepo (transición en transacción); schemas/proposal.py; frontend proposalStatus.js y ProposalStatusControl; scripts/test-proposal-status.sh | I9: =COUNTIF('Casos de prueba'!$B$5:$B$299,A9) | J9: =COUNTIFS('Casos de prueba'!$B$5:$B$299,A9,'Casos de prueba'!$L$5:$L$299,"Aprobado") | K9: =COUNTIFS('Casos de prueba'!$B$5:$B$299,A9,'Casos de prueba'!$L$5:$L$299,"Fallido") | L9: =I9-J9-K9 | M9: =IF(I9=0,"—",J9/I9) | N9: Avance (nota del proyecto, 19-10): backend, frontend y reportes con los estados nuevos, en 3 commits locales sin subir; falta la prueba manual en el navegador. Las transiciones son decisión del equipo, pendiente de acordar con Alloxentric y registrar como D-12. Ejecución 21-10: 19 casos aprobados. Defectos abiertos: RF05-D-001 y RF05-D-002 (Menores). El requerimiento queda validado funcionalmente, no cerrado. | O9: HU-05 | P9: 02, 05
A10: RF-VTA-06 | B10: Firma electrónica | C10: Media | D10: Diferido | E10: Parcial | F10: Media | G10: — | H10: (sin código; solo marcar Firmada con documento adjunto) | I10: =COUNTIF('Casos de prueba'!$B$5:$B$299,A10) | J10: =COUNTIFS('Casos de prueba'!$B$5:$B$299,A10,'Casos de prueba'!$L$5:$L$299,"Aprobado") | K10: =COUNTIFS('Casos de prueba'!$B$5:$B$299,A10,'Casos de prueba'!$L$5:$L$299,"Fallido") | L10: =I10-J10-K10 | M10: =IF(I10=0,"—",J10/I10) | N10: Parcial: solo se prueba marcar la propuesta como Firmada adjuntando el documento firmado (D-04). La integración con un proveedor de firma queda fuera. | O10: HU-06 | P10: 04
A11: RF-VTA-07 | B11: Plantillas de propuestas | C11: Media | D11: Parcial | E11: Sí | F11: Media | G11: R-09 | H11: routers/templates.py | I11: =COUNTIF('Casos de prueba'!$B$5:$B$299,A11) | J11: =COUNTIFS('Casos de prueba'!$B$5:$B$299,A11,'Casos de prueba'!$L$5:$L$299,"Aprobado") | K11: =COUNTIFS('Casos de prueba'!$B$5:$B$299,A11,'Casos de prueba'!$L$5:$L$299,"Fallido") | L11: =I11-J11-K11 | M11: =IF(I11=0,"—",J11/I11) | O11: HU-07 | P11: 08
A12: RF-VTA-08 | B12: Sales enablement | C12: Media | D12: Existe | E12: Sí | F12: Media | G12: — | H12: routers/sales_enablement.py (rama feature/sales-enablement) | I12: =COUNTIF('Casos de prueba'!$B$5:$B$299,A12) | J12: =COUNTIFS('Casos de prueba'!$B$5:$B$299,A12,'Casos de prueba'!$L$5:$L$299,"Aprobado") | K12: =COUNTIFS('Casos de prueba'!$B$5:$B$299,A12,'Casos de prueba'!$L$5:$L$299,"Fallido") | L12: =I12-J12-K12 | M12: =IF(I12=0,"—",J12/I12) | N12: Integra los 37 casos del plan propio (RF08-CP-01 a 37, uno pasa a RF-VTA-01): todos aprobados; 7 defectos corregidos (hoja Defectos). | O12: HU-08 | P12: 11
A13: RF-VTA-09 | B13: Asistente conversacional de ventas | C13: Media | D13: Parcial | E13: Sí | F13: Media | G13: — | H13: routers/chat.py; routers/assistant.py | I13: =COUNTIF('Casos de prueba'!$B$5:$B$299,A13) | J13: =COUNTIFS('Casos de prueba'!$B$5:$B$299,A13,'Casos de prueba'!$L$5:$L$299,"Aprobado") | K13: =COUNTIFS('Casos de prueba'!$B$5:$B$299,A13,'Casos de prueba'!$L$5:$L$299,"Fallido") | L13: =I13-J13-K13 | M13: =IF(I13=0,"—",J13/I13) | O13: HU-09 | P13: 12
A14: RF-VTA-10 | B14: Reportes de pipeline | C14: Media | D14: Parcial | E14: Sí | F14: Media | G14: — | H14: routers/reports.py | I14: =COUNTIF('Casos de prueba'!$B$5:$B$299,A14) | J14: =COUNTIFS('Casos de prueba'!$B$5:$B$299,A14,'Casos de prueba'!$L$5:$L$299,"Aprobado") | K14: =COUNTIFS('Casos de prueba'!$B$5:$B$299,A14,'Casos de prueba'!$L$5:$L$299,"Fallido") | L14: =I14-J14-K14 | M14: =IF(I14=0,"—",J14/I14) | O14: HU-10 | P14: 13
A15: RF-VTA-11 | B15: Historial de versiones | C15: Baja | D15: Parcial | E15: Sí | F15: Baja | G15: — | H15: routers/proposals.py (versiones) | I15: =COUNTIF('Casos de prueba'!$B$5:$B$299,A15) | J15: =COUNTIFS('Casos de prueba'!$B$5:$B$299,A15,'Casos de prueba'!$L$5:$L$299,"Aprobado") | K15: =COUNTIFS('Casos de prueba'!$B$5:$B$299,A15,'Casos de prueba'!$L$5:$L$299,"Fallido") | L15: =I15-J15-K15 | M15: =IF(I15=0,"—",J15/I15) | O15: HU-11 | P15: 09
A16: RF-VTA-12 | B16: Exportación de propuestas | C16: Media | D16: Existe | E16: Sí | F16: Media | G16: R-09 | H16: routers/proposals.py (descarga) | I16: =COUNTIF('Casos de prueba'!$B$5:$B$299,A16) | J16: =COUNTIFS('Casos de prueba'!$B$5:$B$299,A16,'Casos de prueba'!$L$5:$L$299,"Aprobado") | K16: =COUNTIFS('Casos de prueba'!$B$5:$B$299,A16,'Casos de prueba'!$L$5:$L$299,"Fallido") | L16: =I16-J16-K16 | M16: =IF(I16=0,"—",J16/I16) | N16: Incluye 5 pruebas de exportación que vienen de RF-VTA-01 (RF01-PA-23 a 27). Ejecución 21-10: de los 10 casos, 7 aprobados y 3 fallidos (CP-047, 048 y 145). Reprueba tras corregir (21 y 22-10): los 10 aprobados. Defectos RF12-D-001 y 005 (Mayores) y RF12-D-002 y 003 (Menores), corregidos (commits c2e92ed, d0d8264, c21ea02, d9cab02 y 87b69e5). Queda abierto RF12-D-007 (Menor): al guardar en el editor, un h2 pegado, un h4 y las citas pierden el formato; el texto llega completo. Validado funcionalmente, no cerrado. Cierre formal por decidir. | O16: HU-12 | P16: 06
A17: RF-VTA-13 | B17: Configuración y ejecución del pipeline de prospección | C17: Media (propuesta) | D17: Existe | E17: Sí | F17: Media | G17: R-01 | H17: routers/pipeline.py; core/pipeline_constants.py | I17: =COUNTIF('Casos de prueba'!$B$5:$B$299,A17) | J17: =COUNTIFS('Casos de prueba'!$B$5:$B$299,A17,'Casos de prueba'!$L$5:$L$299,"Aprobado") | K17: =COUNTIFS('Casos de prueba'!$B$5:$B$299,A17,'Casos de prueba'!$L$5:$L$299,"Fallido") | L17: =I17-J17-K17 | M17: =IF(I17=0,"—",J17/I17) | N17: Ejecución 21-10: de los 9 casos, 6 aprobados y 3 fallidos (CP-050, 148 y 149). Reprueba tras corregir (22-10): los 9 aprobados. Defectos RF13-D-001, 003 y 004 (Mayores) y RF13-D-002 (Menor), corregidos (commits 1bd2f41, b1e9bd5, 0fcd607 y ae26427); ninguno abierto. Sin modelo ni fuentes reales: la puntuación, los leads y la redirección hacia IP interna quedan cubiertos solo por pruebas unitarias. Cambia el comportamiento del Agente 1 (RF-VTA-14): ahora una fuente que falla deja la ejecución en «partial» con un error por fuente. Validado funcionalmente, no cerrado. | O17: HU-15 | P17: 16
A18: RF-VTA-14 | B18: Detección y calificación de vacantes (Agente 1) | C18: Media (propuesta) | D18: Existe | E18: Sí | F18: Alta | G18: R-01 | H18: services/job_scout_service.py; routers/leads.py; workers/tasks/pipeline_tasks.py | I18: =COUNTIF('Casos de prueba'!$B$5:$B$299,A18) | J18: =COUNTIFS('Casos de prueba'!$B$5:$B$299,A18,'Casos de prueba'!$L$5:$L$299,"Aprobado") | K18: =COUNTIFS('Casos de prueba'!$B$5:$B$299,A18,'Casos de prueba'!$L$5:$L$299,"Fallido") | L18: =I18-J18-K18 | M18: =IF(I18=0,"—",J18/I18) | N18: CP-058 (fuentes reales) bloqueado: el cliente aún no entrega las páginas de oportunidades. Ejecución 21-10: de los 13 casos, 7 aprobados, 5 fallidos (CP-057, 094, 096, 154 y 155) y 1 bloqueado (CP-058, sin fuentes reales). Defectos: RF14-D-001 (Mayor), RF14-D-002 y 003 (Menores); CP-057, 094 y 154 fallan por RF13-D-003. Se probó con red y modelo simulados (prueban la lógica, no la calidad). No cerrado. v1.10 (reprueba tras corregir, 22-10): de los 13 casos, 12 Aprobados y 1 Bloqueado (CP-058, sin fuentes reales). CP-057, 094 y 154 pasan por la corrección de RF13-D-003; CP-096 y CP-155 por RF14-D-001 y RF14-D-002. RF14-D-001 a 003 Corregidos. No se puede cerrar hasta ejecutar CP-058. | O18: HU-16 | P18: 16
A19: RF-VTA-15 | B19: Identificación de contactos de contratación (Agente 2) | C19: Baja (propuesta) | D19: Diferido | E19: No | F19: — | G19: — | H19: schemas/contact.py (solo esquema) | I19: =COUNTIF('Casos de prueba'!$B$5:$B$299,A19) | J19: =COUNTIFS('Casos de prueba'!$B$5:$B$299,A19,'Casos de prueba'!$L$5:$L$299,"Aprobado") | K19: =COUNTIFS('Casos de prueba'!$B$5:$B$299,A19,'Casos de prueba'!$L$5:$L$299,"Fallido") | L19: =I19-J19-K19 | M19: =IF(I19=0,"—",J19/I19) | N19: Diferido (D-07): depende de un proveedor externo de datos de contacto; hoy solo existen esquemas de datos. | O19: — | P19: —
A20: RF-VTA-16 | B20: Redacción y revisión de correos de prospección (Agente 3) | C20: Media (propuesta) | D20: Parcial | E20: Sí | F20: Media | G20: R-04 | H20: routers/outreach.py; schemas/outreach_email.py | I20: =COUNTIF('Casos de prueba'!$B$5:$B$299,A20) | J20: =COUNTIFS('Casos de prueba'!$B$5:$B$299,A20,'Casos de prueba'!$L$5:$L$299,"Aprobado") | K20: =COUNTIFS('Casos de prueba'!$B$5:$B$299,A20,'Casos de prueba'!$L$5:$L$299,"Fallido") | L20: =I20-J20-K20 | M20: =IF(I20=0,"—",J20/I20) | O20: HU-17 | P20: 17
A21: RF-VTA-17 | B21: Escaneo programado del pipeline | C21: Baja (propuesta) | D21: Diferido | E21: No | F21: — | G21: — | H21: workers/celery_app.py; analisis-worker-serverless.md | I21: =COUNTIF('Casos de prueba'!$B$5:$B$299,A21) | J21: =COUNTIFS('Casos de prueba'!$B$5:$B$299,A21,'Casos de prueba'!$L$5:$L$299,"Aprobado") | K21: =COUNTIFS('Casos de prueba'!$B$5:$B$299,A21,'Casos de prueba'!$L$5:$L$299,"Fallido") | L21: =I21-J21-K21 | M21: =IF(I21=0,"—",J21/I21) | N21: Diferido (D-07). Revisar: el backend corre en Render con un worker (start.sh), lo que podría levantar la restricción original. | O21: — | P21: —
A22: RNF-01 | B22: Control de acceso por rol | C22: — | D22: Parcial | E22: Sí | F22: Alta | G22: — | H22: (transversal: todos los routers) | I22: =COUNTIF('Casos de prueba'!$B$5:$B$299,A22) | J22: =COUNTIFS('Casos de prueba'!$B$5:$B$299,A22,'Casos de prueba'!$L$5:$L$299,"Aprobado") | K22: =COUNTIFS('Casos de prueba'!$B$5:$B$299,A22,'Casos de prueba'!$L$5:$L$299,"Fallido") | L22: =I22-J22-K22 | M22: =IF(I22=0,"—",J22/I22) | N22: El criterio incluye aprobar descuentos, pero ningún RF define la función de descuentos; esa parte queda sin objeto de prueba hasta definirla. | O22: HU-13 | P22: 14
A23: RNF-02 | B23: Trazabilidad y auditoría | C23: — | D23: Parcial | E23: Sí | F23: Media | G23: — | H23: middleware/audit.py | I23: =COUNTIF('Casos de prueba'!$B$5:$B$299,A23) | J23: =COUNTIFS('Casos de prueba'!$B$5:$B$299,A23,'Casos de prueba'!$L$5:$L$299,"Aprobado") | K23: =COUNTIFS('Casos de prueba'!$B$5:$B$299,A23,'Casos de prueba'!$L$5:$L$299,"Fallido") | L23: =I23-J23-K23 | M23: =IF(I23=0,"—",J23/I23) | O23: HU-14 | P23: 15
A24: RNF-03 | B24: Rendimiento | C24: — | D24: Parcial | E24: Sí | F24: Alta | G24: R-02, R-03 | H24: (transversal: generación de propuestas) | I24: =COUNTIF('Casos de prueba'!$B$5:$B$299,A24) | J24: =COUNTIFS('Casos de prueba'!$B$5:$B$299,A24,'Casos de prueba'!$L$5:$L$299,"Aprobado") | K24: =COUNTIFS('Casos de prueba'!$B$5:$B$299,A24,'Casos de prueba'!$L$5:$L$299,"Fallido") | L24: =I24-J24-K24 | M24: =IF(I24=0,"—",J24/I24) | O24: HU-01, HU-18 | P24: —
A25: RNF-04 | B25: Cumplimiento y condiciones contractuales | C25: — | D25: Parcial | E25: Sí | F25: Media | G25: R-09 | H25: routers/templates.py | I25: =COUNTIF('Casos de prueba'!$B$5:$B$299,A25) | J25: =COUNTIFS('Casos de prueba'!$B$5:$B$299,A25,'Casos de prueba'!$L$5:$L$299,"Aprobado") | K25: =COUNTIFS('Casos de prueba'!$B$5:$B$299,A25,'Casos de prueba'!$L$5:$L$299,"Fallido") | L25: =I25-J25-K25 | M25: =IF(I25=0,"—",J25/I25) | O25: HU-07 | P25: —
A26: RNF-05 | B26: Disponibilidad e integración | C26: — | D26: Parcial | E26: Sí | F26: Alta | G26: R-03 | H26: (transversal; manual de despliegue) | I26: =COUNTIF('Casos de prueba'!$B$5:$B$299,A26) | J26: =COUNTIFS('Casos de prueba'!$B$5:$B$299,A26,'Casos de prueba'!$L$5:$L$299,"Aprobado") | K26: =COUNTIFS('Casos de prueba'!$B$5:$B$299,A26,'Casos de prueba'!$L$5:$L$299,"Fallido") | L26: =I26-J26-K26 | M26: =IF(I26=0,"—",J26/I26) | O26: HU-18 | P26: 18
A27: RNF-06 | B27: Procesamiento asíncrono de tareas pesadas | C27: — | D27: Parcial | E27: Sí | F27: Alta | G27: R-03, R-05 | H27: workers/celery_app.py; workers/tasks/*; routers/tasks.py; docker-compose.yml | I27: =COUNTIF('Casos de prueba'!$B$5:$B$299,A27) | J27: =COUNTIFS('Casos de prueba'!$B$5:$B$299,A27,'Casos de prueba'!$L$5:$L$299,"Aprobado") | K27: =COUNTIFS('Casos de prueba'!$B$5:$B$299,A27,'Casos de prueba'!$L$5:$L$299,"Fallido") | L27: =I27-J27-K27 | M27: =IF(I27=0,"—",J27/I27) | O27: HU-18 | P27: 18
A28: RNF-07 | B28: Estándares transversales de Alloxentric | C28: — | D28: Diferido | E28: No | F28: — | G28: — | H28: (sin código) | I28: =COUNTIF('Casos de prueba'!$B$5:$B$299,A28) | J28: =COUNTIFS('Casos de prueba'!$B$5:$B$299,A28,'Casos de prueba'!$L$5:$L$299,"Aprobado") | K28: =COUNTIFS('Casos de prueba'!$B$5:$B$299,A28,'Casos de prueba'!$L$5:$L$299,"Fallido") | L28: =I28-J28-K28 | M28: =IF(I28=0,"—",J28/I28) | N28: Diferido (D-10): multi-tenancy, feature gating, internacionalización y tema oscuro no condicionan el cierre de esta etapa. | O28: — | P28: —
A29: TRANSV | B29: Pruebas transversales (cobertura, E2E, regresión, dependencias) | C29: — | D29: — | E29: Sí | F29: Alta | G29: R-13 | H29: (todo el backend crítico) | I29: =COUNTIF('Casos de prueba'!$B$5:$B$299,A29) | J29: =COUNTIFS('Casos de prueba'!$B$5:$B$299,A29,'Casos de prueba'!$L$5:$L$299,"Aprobado") | K29: =COUNTIFS('Casos de prueba'!$B$5:$B$299,A29,'Casos de prueba'!$L$5:$L$299,"Fallido") | L29: =I29-J29-K29 | M29: =IF(I29=0,"—",J29/I29) | O29: — | P29: —
A30: Total | I30: =SUM(I5:I29) | J30: =SUM(J5:J29) | K30: =SUM(K5:K29) | L30: =SUM(L5:L29) | M30: =IF(I30=0,"—",J30/I30)
A32: Filas en gris: requerimientos fuera del alcance de pruebas. RF-VTA-06 se prueba solo en su parte parcial.

Sheet Resumen
A1: Resumen de ejecución
A2: Se actualiza solo a medida que se completa la columna Resultado.
A4: Total de casos
A5: Casos | B5: =COUNTA('Casos de prueba'!$A$5:$A$299)
A6: Ejecutados (Aprobado + Fallido + Bloqueado) | B6: =B5-COUNTIF('Casos de prueba'!$L$5:$L$299,"Pendiente")
A7: % de ejecución | B7: =IF(B5=0,0,B6/B5)
A8: % aprobado sobre ejecutados | B8: =IF(B6=0,"—",COUNTIF('Casos de prueba'!$L$5:$L$299,"Aprobado")/B6)
A10: Por resultado
A11: Categoría | B11: Casos | C11: % del total
A12: Pendiente | B12: =COUNTIF('Casos de prueba'!$L$5:$L$299,A12) | C12: =IF($B$5=0,0,B12/$B$5)
A13: Aprobado | B13: =COUNTIF('Casos de prueba'!$L$5:$L$299,A13) | C13: =IF($B$5=0,0,B13/$B$5)
A14: Fallido | B14: =COUNTIF('Casos de prueba'!$L$5:$L$299,A14) | C14: =IF($B$5=0,0,B14/$B$5)
A15: Bloqueado | B15: =COUNTIF('Casos de prueba'!$L$5:$L$299,A15) | C15: =IF($B$5=0,0,B15/$B$5)
A17: Por prioridad
A18: Categoría | B18: Casos | C18: % del total
A19: Alta | B19: =COUNTIF('Casos de prueba'!$I$5:$I$299,A19) | C19: =IF($B$5=0,0,B19/$B$5)
A20: Media | B20: =COUNTIF('Casos de prueba'!$I$5:$I$299,A20) | C20: =IF($B$5=0,0,B20/$B$5)
A21: Baja | B21: =COUNTIF('Casos de prueba'!$I$5:$I$299,A21) | C21: =IF($B$5=0,0,B21/$B$5)
A23: Por tipo de prueba
A24: Categoría | B24: Casos | C24: % del total
A25: Calidad | B25: =COUNTIF('Casos de prueba'!$G$5:$G$299,A25) | C25: =IF($B$5=0,0,B25/$B$5)
A26: Despliegue | B26: =COUNTIF('Casos de prueba'!$G$5:$G$299,A26) | C26: =IF($B$5=0,0,B26/$B$5)
A27: Funcional | B27: =COUNTIF('Casos de prueba'!$G$5:$G$299,A27) | C27: =IF($B$5=0,0,B27/$B$5)
A28: Integración | B28: =COUNTIF('Casos de prueba'!$G$5:$G$299,A28) | C28: =IF($B$5=0,0,B28/$B$5)
A29: Regresión | B29: =COUNTIF('Casos de prueba'!$G$5:$G$299,A29) | C29: =IF($B$5=0,0,B29/$B$5)
A30: Rendimiento | B30: =COUNTIF('Casos de prueba'!$G$5:$G$299,A30) | C30: =IF($B$5=0,0,B30/$B$5)
A31: Resiliencia | B31: =COUNTIF('Casos de prueba'!$G$5:$G$299,A31) | C31: =IF($B$5=0,0,B31/$B$5)
A32: Seguridad | B32: =COUNTIF('Casos de prueba'!$G$5:$G$299,A32) | C32: =IF($B$5=0,0,B32/$B$5)
A35: Por nivel
A36: Categoría | B36: Casos | C36: % del total
A37: Unitaria | B37: =COUNTIF('Casos de prueba'!$H$5:$H$299,A37) | C37: =IF($B$5=0,0,B37/$B$5)
A38: Integración | B38: =COUNTIF('Casos de prueba'!$H$5:$H$299,A38) | C38: =IF($B$5=0,0,B38/$B$5)
A39: Sistema | B39: =COUNTIF('Casos de prueba'!$H$5:$H$299,A39) | C39: =IF($B$5=0,0,B39/$B$5)
A40: E2E | B40: =COUNTIF('Casos de prueba'!$H$5:$H$299,A40) | C40: =IF($B$5=0,0,B40/$B$5)
A41: Aceptación | B41: =COUNTIF('Casos de prueba'!$H$5:$H$299,A41) | C41: =IF($B$5=0,0,B41/$B$5)

Sheet Casos de prueba
A1: Casos de prueba
A2: Celdas amarillas: completar durante la ejecución.
A4: ID caso | B4: Requerimiento | C4: Criterio de aceptación cubierto | D4: Caso de prueba | E4: Pasos | F4: Resultado esperado | G4: Tipo | H4: Nivel | I4: Prioridad | J4: Riesgo (PMBOK) | K4: Automatizable | L4: Resultado | M4: Fecha de ejecución | N4: N° defecto | O4: Observaciones | P4: Tipo de evidencia | Q4: Captura sugerida (qué debe mostrar) | R4: Herramienta | S4: Estado de automatización | T4: Prueba automatizada (archivo o ID) | U4: Archivo de evidencia
A5: RF01-PA-01 | B5: RF-VTA-01 | C5: Contexto histórico según cliente y servicio (propuestas de BPO cargadas) | D5: Cargar los 3 Word de ejemplo | E5: Dado un manager, cuando sube los 3 Word de ejemplo. | F5: Aparecen 3 documentos en la lista con sus fragmentos. | G5: Funcional | H5: Sistema | I5: Alta | J5: R-09 | K5: No | L5: Aprobado | M5: 46315 | O5: Origen: CU-01 y PA-01 de los casos de uso de RF-VTA-01 (13-10-2026). Ejecución 20-10 (plan propio de RF-VTA-01, sistema real): PA-01 PASA: HTTP 201, 3 documentos con 3 fragmentos cada uno, los 3 aparecen en la lista. Evidencia: RF-VTA-01_Pruebas_y_Aceptacion/Evidencia/Salidas_de_scripts/PA-01_a_09_12_base_de_conocimiento_20-oct.txt
A6: RF01-PA-02 | B6: RF-VTA-01 | C6: Contexto histórico según cliente y servicio (propuestas de BPO cargadas) | D6: Texto de tablas en Word | E6: Dado un Word con tablas, cuando se procesa. | F6: El texto de la tabla ("Mesa de ayuda", "Precio: 1200") queda en el contenido. | G6: Funcional | H6: Unitaria | I6: Media | J6: — | K6: Sí | L6: Aprobado | M6: 46308 | O6: Origen: CU-01 y PA-02 de los casos de uso de RF-VTA-01 (13-10-2026). Evidencia automática: backend/tests/test_knowledge.py; suite del backend en verde al cierre de ese documento.
A7: RF01-PA-03 | B7: RF-VTA-01 | C7: Contexto histórico según cliente y servicio (propuestas de BPO cargadas) | D7: CSV y Excel con encabezados | E7: Dado un CSV y un Excel con encabezados, cuando se procesan. | F7: Cada fila queda como "Columna: valor". | G7: Funcional | H7: Unitaria | I7: Media | J7: — | K7: Sí | L7: Aprobado | M7: 46308 | O7: Origen: CU-01 y PA-03 de los casos de uso de RF-VTA-01 (13-10-2026). Evidencia automática: backend/tests/test_knowledge.py; suite del backend en verde al cierre de ese documento.
A8: RF01-PA-04 | B8: RF-VTA-01 | C8: Contexto histórico según cliente y servicio (propuestas de BPO cargadas) | D8: Extracción de texto de un PDF | E8: Dado un PDF con texto, cuando se procesa. | F8: Se extrae el texto. | G8: Funcional | H8: Unitaria | I8: Media | J8: — | K8: Sí | L8: Aprobado | M8: 46308 | O8: Origen: CU-01 y PA-04 de los casos de uso de RF-VTA-01 (13-10-2026). Evidencia automática: backend/tests/test_knowledge.py; suite del backend en verde al cierre de ese documento.
A9: RF01-PA-05 | B9: RF-VTA-01 | C9: Contexto histórico según cliente y servicio (propuestas de BPO cargadas) | D9: Rechazo de archivos inválidos | E9: Dado `.doc`, `.exe`, archivo vacío o PDF inválido, cuando se sube. | F9: Se rechaza con un mensaje claro. | G9: Funcional | H9: Integración | I9: Media | J9: — | K9: Sí | L9: Aprobado | M9: 46308 | O9: Origen: CU-01 y PA-05 de los casos de uso de RF-VTA-01 (13-10-2026). Evidencia automática: backend/tests/test_knowledge.py; suite del backend en verde al cierre de ese documento.
A10: RF01-PA-06 | B10: RF-VTA-01 | C10: Contexto histórico según cliente y servicio (propuestas de BPO cargadas) | D10: Carga sin rol manager | E10: Dado un usuario sin rol manager, cuando intenta subir. | F10: Recibe 403. | G10: Seguridad | H10: Integración | I10: Alta | J10: — | K10: Sí | L10: Aprobado | M10: 46308 | O10: Origen: CU-01 y PA-06 de los casos de uso de RF-VTA-01 (13-10-2026). Evidencia automática: backend/tests/test_knowledge.py; suite del backend en verde al cierre de ese documento.
A11: RF01-PA-07 | B11: RF-VTA-01 | C11: Contexto histórico según cliente y servicio (propuestas de BPO cargadas) | D11: Carga mixta (archivo válido e inválido) | E11: Dado un archivo válido y uno inválido, cuando se suben juntos. | F11: El válido se guarda y el inválido se informa. | G11: Funcional | H11: Integración | I11: Media | J11: — | K11: Sí | L11: Aprobado | M11: 46308 | O11: Origen: CU-01 y PA-07 de los casos de uso de RF-VTA-01 (13-10-2026). Evidencia automática: backend/tests/test_knowledge.py; suite del backend en verde al cierre de ese documento.
A12: RF01-PA-08 | B12: RF-VTA-01 | C12: Contexto histórico según cliente y servicio (propuestas de BPO cargadas) | D12: Eliminar documento de otro usuario | E12: Dado un documento de otro usuario, cuando se intenta eliminar. | F12: Recibe 403. | G12: Seguridad | H12: Integración | I12: Alta | J12: — | K12: Sí | L12: Aprobado | M12: 46308 | O12: Origen: CU-02 y PA-08 de los casos de uso de RF-VTA-01 (13-10-2026). Evidencia automática: backend/tests/test_knowledge.py; suite del backend en verde al cierre de ese documento.
A13: RF01-PA-09 | B13: RF-VTA-01 | C13: Contexto histórico según cliente y servicio (propuestas de BPO cargadas) | D13: Eliminar documento propio | E13: Dado un documento propio, cuando el manager lo elimina. | F13: Desaparece de la lista y deja de influir en la generación. | G13: Funcional | H13: Sistema | I13: Media | J13: — | K13: No | L13: Aprobado | M13: 46315 | O13: Origen: CU-02 y PA-09 de los casos de uso de RF-VTA-01 (13-10-2026). Ejecución 20-10 (plan propio de RF-VTA-01, sistema real): PA-09 PASA: DELETE 204 y el documento ya no está en la lista (también en pantalla: CP-09 del plan de RF-VTA-01). Evidencia: RF-VTA-01_Pruebas_y_Aceptacion/Evidencia/Salidas_de_scripts/PA-01_a_09_12_base_de_conocimiento_20-oct.txt; RF-VTA-01_Pruebas_y_Aceptacion/Evidencia/Salidas_de_scripts/CP-01_09_interfaz_documentos_20-oct.txt
A14: RF01-PA-10 | B14: RF-VTA-01 | C14: Contexto histórico según cliente y servicio (propuestas de BPO cargadas) | D14: La búsqueda devuelve fragmentos del servicio pedido | E14: Dado documentos de cobranza, contact center y back office, cuando se busca "cobranza telefónica mora". | F14: Los fragmentos devueltos son de la propuesta de cobranza. | G14: Funcional | H14: Integración | I14: Alta | J14: R-11 | K14: Sí | L14: Aprobado | M14: 46308 | O14: Origen: CU-04 y PA-10 de los casos de uso de RF-VTA-01 (13-10-2026). Evidencia automática: backend/tests/test_knowledge.py; suite del backend en verde al cierre de ese documento.
A15: RF01-PA-11 | B15: RF-VTA-01 | C15: Contexto histórico según cliente y servicio (propuestas de BPO cargadas) | D15: Usuario sin documentos cargados | E15: Dado un usuario sin documentos, cuando se genera. | F15: No se agrega contexto histórico. | G15: Funcional | H15: Integración | I15: Media | J15: R-11 | K15: Sí | L15: Aprobado | M15: 46308 | O15: Origen: CU-04 y PA-11 de los casos de uso de RF-VTA-01 (13-10-2026). Evidencia automática: backend/tests/test_knowledge.py; suite del backend en verde al cierre de ese documento.
A16: RF01-PA-12 | B16: RF-VTA-01 | C16: Contexto histórico según cliente y servicio (propuestas de BPO cargadas) | D16: El contexto solo usa documentos del propio usuario | E16: Dado documentos del usuario, cuando se recupera el contexto. | F16: Solo se consultan los de ese usuario. | G16: Seguridad | H16: Integración | I16: Alta | J16: R-11 | K16: Sí | L16: Aprobado | M16: 46308 | O16: Origen: CU-04 y PA-12 de los casos de uso de RF-VTA-01 (13-10-2026). Evidencia automática: backend/tests/test_knowledge.py; suite del backend en verde al cierre de ese documento.
... A26: RF01-PA-22 | B26: RF-VTA-01 | C26: Borrador editable a partir de cliente, servicio y descripción | D26: Editar y guardar el borrador | E26: Dado un borrador, cuando el usuario edita y guarda. | F26: Al reabrirlo ve su texto, con un solo cuadro de total y una sola aceptación. | G26: Funcional | H26: Integración | I26: Media | J26: — | K26: Parcial | L26: Aprobado | M26: 46315 | O26: Origen: CU-06 y PA-22 de los casos de uso de RF-VTA-01 (13-10-2026). Evidencia automática: frontend/src/__tests__/proposalSections.test.js (parte automática); suite del backend en verde al cierre de ese documento. Parte automática verde; falta la parte manual. Ejecución 20-10 (plan propio de RF-VTA-01, sistema real): PA-22 PASA: al reabrir se ve el texto editado y no se duplican las tablas de precios. La parte visual de la edición fue confirmada por el usuario el 20-10 (CP-24). Evidencia: RF-VTA-01_Pruebas_y_Aceptacion/Evidencia/Salidas_de_scripts/PA-10_a_27_generacion_y_exportacion_20-oct.txt
A27: CP-004 | B27: RF-VTA-01 | C27: Contexto histórico según cliente y servicio | D27: Documentos cargados sin relación con el servicio pedido | E27: Con documentos cargados que no tratan el servicio pedido, generar una propuesta de ese servicio. | F27: No se incluyen fragmentos irrelevantes en el contexto; el borrador no cita propuestas de otro rubro. | G27: Funcional | H27: Integración | I27: Alta | J27: R-11 | K27: Sí | L27: Pendiente | O27: Resultado esperado tomado de CU-04, flujo alternativo A2, de los casos de uso de RF-VTA-01.
A28: CP-100 | B28: RF-VTA-01 | C28: Contexto histórico según cliente y servicio (propuestas de BPO cargadas) | D28: Límites de la carga de documentos | E28: Subir un archivo vacío, uno de más de 10 MB, 11 archivos en una carga y superar el máximo de 200 documentos. | F28: Cada situación se rechaza con un mensaje que indica el límite (CU-01, A3 y A6). | G28: Funcional | H28: Integración | I28: Media | J28: — | K28: Parcial | L28: Pendiente | O28: Tomado de CU-01 (A3, A6); ninguna prueba de aceptación existente lo cubre.
A29: CP-101 | B29: RF-VTA-01 | C29: Todos los criterios | D29: Prueba de punta a punta con el modelo y la base de datos reales | E29: Con DeepSeek y Firestore reales (no simulados): cargar documentos, generar la propuesta desde una oportunidad, editarla y exportarla. | F29: El flujo completo funciona; se registran los tiempos de generación y el consumo de créditos. | G29: Funcional | H29: E2E | I29: Alta | J29: R-02, R-11 | K29: No | L29: Pendiente | O29: Pendiente P7 de los casos de uso de RF-VTA-01: hoy las pruebas automáticas usan datos simulados.
A30: RF08-CP-34 | B30: RF-VTA-01 | C30: El borrador se basa en información cargada y no presenta como reales datos inexistentes | D30: Regresión de RF-VTA-01: propuesta desde una oportunidad | E30: Precondición: Documentos de ejemplo. Regresión RF-VTA-01: crear una propuesta desde una oportunidad y generarla. | F30: La propuesta se genera usando los documentos como contexto, igual que antes de RF-VTA-08 (se refactorizó la recuperación de fuentes). | G30: Regresión | H30: Sistema | I30: Alta | J30: — | K30: No | L30: Aprobado | M30: 46312 | O30: Origen: CP-34 del plan de RF-VTA-08 (—). Obtenido: 17-oct, oportunidad Financiera Horizonte: la tarea quedó «pending» porque el worker de Celery solo escuchaba la cola default y las propuestas van a la cola llm (error de arranque del entorno, no del sistema; se levanta con -Q default,llm). Tras corregirlo, la propuesta se generó en 31 s y usa datos de la propuesta histórica cargada (24x7, centros en Chile y Colombia, más de 12 años, gestión por SLAs) sin nombrar al otro cliente.
A31: CP-006 | B31: RF-VTA-02 | C31: Crear, editar y desactivar servicios | D31: Mantener servicios del catálogo | E31: Como manager: crear un servicio con nombre, descripción, unidad, precio, moneda y condiciones; editarlo; desactivarlo. | F31: Cada operación se guarda y se refleja en el listado con todos los campos. | G31: Funcional | H31: Integración | I31: Alta | J31: R-09 | K31: Sí | L31: Pendiente
A32: CP-007 | B32: RF-VTA-02 | C32: Crear, editar y desactivar servicios | D32: Validación de campos del servicio (negativo) | E32: Crear un servicio con precio negativo, precio vacío o sin moneda. | F32: El sistema rechaza el registro e indica el campo con error. | G32: Funcional | H32: Unitaria | I32: Alta | J32: R-09 | K32: Sí | L32: Pendiente
A33: CP-008 | B33: RF-VTA-02 | C33: Elegir servicios del catálogo con precio precargado | D33: Precarga y ajuste de precio | E33: En el paso 2 de la propuesta, elegir un servicio del catálogo y cambiar el precio. | F33: El precio se precarga desde el catálogo y se puede ajustar en la propuesta sin cambiar el catálogo. | G33: Funcional | H33: Sistema | I33: Alta | J33: R-09 | K33: No | L33: Pendiente
A34: CP-009 | B34: RF-VTA-02 | C34: Desactivar servicios (derivado) | D34: Servicio desactivado no se ofrece | E34: Desactivar un servicio y abrir una propuesta nueva. | F34: El servicio desactivado no aparece entre las opciones; las propuestas ya emitidas lo conservan. | G34: Funcional | H34: Integración | I34: Alta | J34: R-09 | K34: Sí | L34: Pendiente
A35: CP-010 | B35: RF-VTA-02 | C35: Solo manager y admin modifican precios | D35: Permiso de edición de precios | E35: Con un usuario con rol user, intentar crear o cambiar el precio de un servicio. Repetir con manager y admin. | F35: El usuario con rol user recibe rechazo (403); manager y admin pueden hacerlo. | G35: Seguridad | H35: Integración | I35: Alta | J35: R-09 | K35: Sí | L35: Pendiente
A36: CP-011 | B36: RF-VTA-02 | C36: Modificar el catálogo no cambia propuestas emitidas | D36: Propuesta emitida conserva su precio | E36: Emitir una propuesta, luego cambiar el precio del servicio en el catálogo y reabrir la propuesta. | F36: La propuesta emitida mantiene el precio original. | G36: Funcional | H36: Integración | I36: Alta | J36: R-09 | K36: Sí | L36: Pendiente
A37: CP-102 | B37: RF-VTA-02 | C37: Crear, editar y desactivar servicios | D37: Servicio duplicado (negativo) | E37: Como manager, crear dos servicios con el mismo nombre y la misma unidad. | F37: El sistema rechaza el segundo e indica que ya existe. | G37: Funcional | H37: Integración | I37: Media | J37: R-09 | K37: Sí | L37: Pendiente | O37: Comportamiento propuesto por QA; confirmar si se admiten duplicados.
A38: CP-103 | B38: RF-VTA-02 | C38: Crear, editar y desactivar servicios | D38: Valores límite del precio | E38: Crear servicios con precio 0, 0,01, 1.000.000 y 10,555 (tres decimales). | F38: Se rechazan el 0 y el de tres decimales; se aceptan 0,01 y 1.000.000. | G38: Funcional | H38: Unitaria | I38: Alta | J38: R-09 | K38: Sí | L38: Pendiente | O38: Límites propuestos por QA; confirmar con el cliente.
A39: CP-104 | B39: RF-VTA-02 | C39: Crear, editar y desactivar servicios | D39: Servicios en monedas distintas en una propuesta | E39: Elegir en una misma propuesta un servicio en USD y otro en CLP. | F39: El sistema no permite mezclar monedas en una propuesta e informa el motivo. | G39: Funcional | H39: Integración | I39: Media | J39: R-09 | K39: Sí | L39: Pendiente | O39: Comportamiento propuesto por QA; confirmar.
A40: CP-105 | B40: RF-VTA-02 | C40: Crear, editar y desactivar servicios | D40: Búsqueda y filtro del catálogo | E40: Buscar por parte del nombre y filtrar por activos e inactivos. | F40: La lista muestra solo los servicios que coinciden con el texto y el estado elegidos. | G40: Funcional | H40: Sistema | I40: Media | J40: R-09 | K40: Parcial | L40: Pendiente
A41: CP-106 | B41: RF-VTA-02 | C41: Elegir servicios del catálogo con precio precargado | D41: Total de la propuesta con servicios del catálogo | E41: Elegir dos servicios del catálogo con cantidades 3 y 1 y revisar el total. | F41: Los precios se precargan y el total es exactamente la suma de cantidad por precio. | G41: Funcional | H41: Integración | I41: Alta | J41: R-09 | K41: Sí | L41: Pendiente
A42: CP-012 | B42: RF-VTA-03 | C42: El cliente registra industria y tamaño | D42: Registrar industria y tamaño | E42: Crear y luego editar un cliente completando industria y tamaño. | F42: Ambos datos se guardan y se muestran en la ficha del cliente. | G42: Funcional | H42: Integración | I42: Alta | J42: — | K42: Sí | L42: Pendiente
A43: CP-013 | B43: RF-VTA-03 | C43: Propuesta vinculada al cliente e historial | D43: Vínculo propuesta–cliente e historial | E43: Crear dos propuestas para el mismo cliente y abrir su historial. | F43: Cada propuesta guarda el identificador del cliente; el historial lista las dos. | G43: Funcional | H43: Integración | I43: Alta | J43: — | K43: Sí | L43: Pendiente
A44: CP-014 | B44: RF-VTA-03 | C44: Contenido incorpora industria y tamaño | D44: Contenido adaptado al perfil | E44: Generar una propuesta para dos clientes de industrias y tamaños distintos con el mismo servicio. | F44: El texto de cada borrador incorpora la industria y el tamaño de su cliente. | G44: Funcional | H44: Integración | I44: Alta | J44: — | K44: Parcial | L44: Pendiente
A45: CP-015 | B45: RF-VTA-03 | C45: El cliente registra industria y tamaño | D45: Cliente existente sin industria ni tamaño (regresión) | E45: Abrir y generar una propuesta para un cliente creado antes del cambio, sin esos datos. | F45: El sistema no falla; solicita o ignora los datos faltantes de forma controlada. | G45: Regresión | H45: Integración | I45: Alta | J45: — | K45: Sí | L45: Pendiente
A46: CP-107 | B46: RF-VTA-03 | C46: El cliente registra industria y tamaño | D46: Tamaño con un valor no previsto (negativo) | E46: Guardar un cliente con tamaño fuera de los valores definidos. | F46: El sistema rechaza el valor y muestra un mensaje con los valores válidos. | G46: Funcional | H46: Integración | I46: Media | J46: — | K46: Sí | L46: Pendiente | O46: La lista de valores de industria y tamaño debe definirse.
A47: CP-108 | B47: RF-VTA-03 | C47: El cliente registra industria y tamaño | D47: Importación CSV con industria y tamaño | E47: Importar un CSV con las dos columnas nuevas, una fila válida y una inválida. | F47: La fila válida se guarda con sus datos y la inválida se informa sin detener la importación. | G47: Funcional | H47: Integración | I47: Media | J47: — | K47: Sí | L47: Pendiente | O47: Posible evidencia: tests/test_customers.py (por revisar).
A48: CP-109 | B48: RF-VTA-03 | C48: Propuesta vinculada al cliente e historial | D48: Eliminar un cliente con propuestas (negativo) | E48: Intentar eliminar un cliente que tiene propuestas. | F48: El sistema impide la eliminación e indica cuántas propuestas tiene. | G48: Funcional | H48: Integración | I48: Media | J48: — | K48: Sí | L48: Pendiente | O48: Comportamiento propuesto por QA; confirmar.
A49: CP-110 | B49: RF-VTA-03 | C49: Propuesta vinculada al cliente e historial | D49: Historial ordenado | E49: Abrir el historial de un cliente con cuatro propuestas de fechas y estados distintos. | F49: Las propuestas aparecen de la más reciente a la más antigua, con su estado. | G49: Funcional | H49: Integración | I49: Media | J49: — | K49: Sí | L49: Pendiente
A50: CP-111 | B50: RF-VTA-03 | C50: Propuesta vinculada al cliente e historial | D50: Aislamiento de clientes entre usuarios | E50: Con el usuario B, consultar un cliente y su historial del usuario A. | F50: Ambas consultas se rechazan (403 o 404) y no devuelven datos. | G50: Seguridad | H50: Integración | I50: Alta | J50: — | K50: Sí | L50: Pendiente
A51: CP-016 | B51: RF-VTA-04 | C51: El CRM contiene contacto y negocio con monto | D51: Envío a HubSpot (cuenta de desarrollo) | E51: Enviar una propuesta al CRM con una cuenta de desarrollo de HubSpot. | F51: El CRM contiene el contacto y el negocio con el monto de la propuesta. | G51: Integración | H51: Sistema | I51: Alta | J51: R-08 | K51: Parcial | L51: Aprobado | M51: 46317 | O51: Ejecución 22-10: Emulador: 200; 1 contacto (email, nombre, apellido, empresa) y 1 negocio con amount=12500 y título, asociado al contacto; crmSync «synced» con IDs. 7/7 verificaciones. HubSpot REAL (cuenta de desarrollo, 22-10): contacto y negocio creados con los datos y el monto 12 500 y negocio asociado al contacto, leídos de vuelta desde la API de HubSpot (4/4 verificaciones); registros borrados al final. Pantalla (app real): botón «Subir al CRM» visible en es, en («Upload to CRM») y pt («Enviar ao CRM»), con temas claro, oscuro y noon y en ancho de celular; aviso «Proposal sent to HubSpot.» tras enviar. En celular los botones del pie se reparten en filas y el pie queda fijo abajo, con todos visibles sin desplazar (CP-016g, CP-016j); el aviso de éxito sale en el idioma de la interfaz (CP-016b en español, CP-016i en inglés). Pantalla con CRM real: CP-016k. [22-10-2026; API · script · emulador · pantalla · CRM real] | P51: Captura y reporte | Q51: Propuesta abierta con el botón «Subir al CRM» y el aviso de envío exitoso; contacto y negocio en HubSpot con el monto 12 500. | R51: Script Python (httpx) + Chrome (CDP) + CRM real | S51: Automatizada | T51: Evidencia/Scripts/run_rfvta04_api.py; Evidencia/Scripts/run_rfvta04_real.py; backend/tests/test_proposals_crm.py | U51: Evidencia/Salidas_de_scripts/CP-016_envio_HubSpot_emulador_22-oct.txt; Evidencia/Archivos_generados/CP-016_estado_HubSpot.json; Evidencia/Capturas/CP-016a_propuesta_abierta_boton_Subir_al_CRM.png; Evidencia/Capturas/CP-016b_envio_exitoso_aviso_HubSpot.png; Evidencia/Capturas/CP-016c_tema_oscuro_propuesta_abierta.png; Evidencia/Capturas/CP-016d_tema_noon_propuesta_abierta.png; Evidencia/Capturas/CP-016e_idioma_en_boton_CRM.png; Evidencia/Capturas/CP-016f_idioma_pt_boton_CRM.png; Evidencia/Capturas/CP-016g_celular_propuesta_abierta.png; Evidencia/Capturas/CP-016h_celular_envio_exitoso.png; Evidencia/Capturas/CP-016i_idioma_en_envio_exitoso.png; Evidencia/Capturas/CP-016j_celular_pie_con_todos_los_botones.png; Evidencia/Capturas/CP-016k_CRM_REAL_HubSpot_envio_exitoso.png; Evidencia/Salidas_de_scripts/CP-016_REAL_CRM_22-oct.txt; Evidencia/Archivos_generados/CP-016_REAL_HubSpot_estado.json
A52: CP-017 | B52: RF-VTA-04 | C52: El CRM contiene contacto y negocio con monto | D52: Envío a Salesforce (cuenta de desarrollo) | E52: Repetir el envío con una cuenta de desarrollo de Salesforce (si hay cuenta disponible; basta con probar un CRM real). | F52: El CRM contiene el contacto y la oportunidad con el monto de la propuesta. | G52: Integración | H52: Sistema | I52: Alta | J52: R-08 | K52: Parcial | L52: Aprobado | M52: 46317 | O52: Ejecución 22-10: Emulador: 200 con provider=salesforce; 1 cuenta «Acme Chile SpA», 1 contacto, 1 oportunidad con Amount=12500 y rol de contacto. 5/5 verificaciones. Salesforce REAL (org de desarrollo, 22-10): cuenta, contacto y oportunidad creados con Amount 12500 y rol de contacto, leídos de vuelta con SOQL (5/5 verificaciones); registros borrados al final. Pantalla: aviso «Proposal sent to Salesforce.». Pantalla con CRM real: CP-017b. [22-10-2026; API · script · emulador · pantalla · CRM real] | P52: Captura y reporte | Q52: Aviso de envío exitoso a Salesforce; cuenta, contacto y oportunidad con Amount 12500 en el CRM. | R52: Script Python (httpx) + Chrome (CDP) + CRM real | S52: Automatizada | T52: Evidencia/Scripts/run_rfvta04_api.py; Evidencia/Scripts/run_rfvta04_real.py; backend/tests/test_proposals_crm.py | U52: Evidencia/Salidas_de_scripts/CP-017_envio_Salesforce_emulador_22-oct.txt; Evidencia/Archivos_generados/CP-017_estado_Salesforce.json; Evidencia/Capturas/CP-017_envio_exitoso_aviso_Salesforce.png; Evidencia/Capturas/CP-017b_CRM_REAL_Salesforce_envio_exitoso.png; Evidencia/Salidas_de_scripts/CP-017_REAL_CRM_22-oct.txt; Evidencia/Archivos_generados/CP-017_REAL_Salesforce_estado.json
A53: CP-018 | B53: RF-VTA-04 | C53: Reenviar no duplica | D53: Reenvío actualiza y no duplica | E53: Enviar la misma propuesta dos veces, cambiando el monto entre envíos. | F53: Un solo contacto y un solo negocio en el CRM, con el monto actualizado. | G53: Integración | H53: Sistema | I53: Alta | J53: R-08 | K53: Parcial | L53: Aprobado | M53: 46317 | O53: Ejecución 22-10: Ambos proveedores: 2º envío 200; 1 contacto, 1 negocio/oportunidad (y 1 cuenta en Salesforce), monto 18000. 9/9 verificaciones. Salvedad: el emulador indexa al instante; HubSpot real puede tardar (L-02). Pantalla: segundo envío con monto 18 000 → aviso de éxito; el CRM quedó con 1 contacto y 1 negocio de monto 18000. CRM REAL: HubSpot, 3 reenvíos inmediatos (15 000, 18 000, 21 000) y uno posterior (9 000) → 1 contacto, 1 negocio y el mismo ID, sin duplicados pese a la indexación (6/6); Salesforce, 2 reenvíos → 1 cuenta, 1 contacto y 1 oportunidad con monto 18 000 (2/2). [22-10-2026; API · script · emulador · pantalla · CRM real] | P53: Captura y reporte | Q53: Primer envío y reenvío con monto 18 000; el CRM con un solo contacto y un solo negocio. | R53: Script Python (httpx) + Chrome (CDP) + CRM real | S53: Automatizada | T53: Evidencia/Scripts/run_rfvta04_api.py; Evidencia/Scripts/run_rfvta04_real.py; backend/tests/test_proposals_crm.py | U53: Evidencia/Salidas_de_scripts/CP-018_reenvio_no_duplica_22-oct.txt; Evidencia/Archivos_generados/CP-018_estado_hubspot.json; Evidencia/Archivos_generados/CP-018_estado_salesforce.json; Evidencia/Capturas/CP-018a_primer_envio.png; Evidencia/Capturas/CP-018b_reenvio_monto_18000.png; Evidencia/Salidas_de_scripts/CP-018_REAL_CRM_22-oct.txt; Evidencia/Salidas_de_scripts/CP-018_Salesforce_REAL_CRM_22-oct.txt; Evidencia/Archivos_generados/CP-018_REAL_HubSpot_estado.json
A54: CP-019 | B54: RF-VTA-04 | C54: Error del CRM visible y registrado | D54: Error del CRM se muestra y se registra | E54: Enviar con credenciales inválidas o simulando caída del CRM. | F54: El usuario ve el error y este queda registrado en la propuesta. | G54: Resiliencia | H54: Integración | I54: Alta | J54: R-08 | K54: Sí | L54: Aprobado | M54: 46317 | N54: RF04-D-001, RF04-D-002 | O54: Ejecución 22-10: Reprueba tras la corrección: (a) credenciales inválidas: 401 con mensaje visible y crmSync «failed» con el error; (b)(c) CRM caído (HubSpot y Salesforce): 502 «No se pudo conectar con …» y crmSync «failed»; (d) 5xx: 502 registrado. 6/6 verificaciones. Antes: 2/6 (RF04-D-001, D-002; salida en ANTES_de_corregir/). Pantalla: con el CRM caído se ve completo «No se pudo conectar con HubSpot. Revisa que el servicio esté disponible e inténtalo de nuevo.» (antes de corregir D-005 lo tapaba «Server error. Please try again.»). [22-10-2026; API · script · emulador · pantalla] | P54: Captura y reporte | Q54: Aviso «No se pudo conectar con HubSpot…» con el CRM caído y crmSync «failed» en la propuesta. | R54: Script Python (httpx) + Chrome (CDP) | S54: Automatizada | T54: Evidencia/Scripts/run_rfvta04_api.py; backend/tests/test_proposals_crm.py | U54: Evidencia/Salidas_de_scripts/CP-019_error_CRM_visible_y_registrado_22-oct.txt; Evidencia/Archivos_generados/CP-019_propuestas_tras_errores.json; Evidencia/Capturas/CP-019a_CRM_caido_aviso_No_se_pudo_conectar.png
A55: CP-020 | B55: RF-VTA-04 | C55: Sincronización en un solo sentido (D-03) | D55: Sincronización unidireccional | E55: Modificar el negocio directamente en el CRM y consultar la propuesta. | F55: La propuesta no cambia; solo hay flujo de propuesta hacia el CRM. | G55: Funcional | H55: Sistema | I55: Alta | J55: R-08 | K55: Parcial | L55: Aprobado | M55: 46317 | O55: Ejecución 22-10: Título, monto, correo, empresa, nombre y crmSync idénticos antes/después; la consulta hizo 0 llamadas al CRM; git grep «webhook» en proposals.py, settings.py y crm_service.py: sin resultados. 4/4 verificaciones. [22-10-2026; API · script · revisión de código] | P55: Reporte de pruebas | Q55: Propuesta antes y después de editar el negocio en el CRM, sin cambios. | R55: Script Python (httpx) | S55: Automatizada | T55: Evidencia/Scripts/run_rfvta04_api.py; backend/tests/test_proposals_crm.py | U55: Evidencia/Salidas_de_scripts/CP-020_sincronizacion_unidireccional_22-oct.txt; Evidencia/Archivos_generados/CP-020_propuesta_antes_y_despues.json
A56: CP-088 | B56: RF-VTA-04 | C56: Un error del CRM se muestra al usuario y queda registrado | D56: Propuesta sin correo del cliente (negativo) | E56: Enviar al CRM una propuesta cuyo cliente no tiene correo. | F56: El sistema rechaza el envío e indica que falta el correo; no se crea nada en el CRM. | G56: Funcional | H56: Integración | I56: Media | J56: R-08 | K56: Sí | L56: Aprobado | M56: 46317 | N56: RF04-D-004 | O56: Ejecución 22-10: Nulo y vacío: 400 «La propuesta no tiene un email de cliente…», 0 llamadas al CRM, propuesta intacta. 5/5 verificaciones del caso. Complementario (reprueba tras corregir D-004): correo « » y «no-es-un-correo» se rechazan con 400 antes de llamar al CRM (7/7 verificaciones; antes llegaban al CRM y volvían como 502). Pantalla: la propuesta sin correo abre el recuadro «Client email required»; con «no-es-un-correo» el recuadro rechaza el formato con «Ingresa un correo válido…» antes de enviar (el recuadro y los avisos están traducidos). [22-10-2026; API · script · emulador · pantalla] | P56: Captura y reporte | Q56: Recuadro «Client email required» y rechazo del correo mal formado antes de enviar. | R56: Script Python (httpx) + Chrome (CDP) | S56: Automatizada | T56: Evidencia/Scripts/run_rfvta04_api.py; backend/tests/test_proposals_crm.py | U56: Evidencia/Salidas_de_scripts/CP-088_propuesta_sin_correo_22-oct.txt; Evidencia/Archivos_generados/CP-088_llamadas_al_CRM.json; Evidencia/Capturas/CP-088a_pide_correo_del_cliente.png; Evidencia/Capturas/CP-088b_correo_mal_formado_rechazado.png
A57: CP-089 | B57: RF-VTA-04 | C57: Sin credenciales configuradas, el sistema muestra un mensaje claro | D57: CRM no configurado (negativo) | E57: Enviar una propuesta al CRM sin integración activa en Ajustes. | F57: El sistema muestra un mensaje claro y no modifica la propuesta. | G57: Funcional | H57: Integración | I57: Media | J57: R-08 | K57: Sí | L57: Aprobado | M57: 46317 | O57: Ejecución 22-10: 4 variantes: 400 «No hay una integración de CRM configurada en Ajustes.», propuesta sin cambios, 0 llamadas al CRM. Complementarios: ajena 403, inexistente 404, «zoho» 400, sin sesión 403, token inválido 401. 12/12 verificaciones. Pantalla: aviso «No hay una integración de CRM configurada en Ajustes.». [22-10-2026; API · script · pantalla] | P57: Captura y reporte | Q57: Aviso «No hay una integración de CRM configurada en Ajustes.». | R57: Script Python (httpx) + Chrome (CDP) | S57: Automatizada | T57: Evidencia/Scripts/run_rfvta04_api.py; backend/tests/test_proposals_crm.py | U57: Evidencia/Salidas_de_scripts/CP-089_CRM_no_configurado_22-oct.txt; Evidencia/Capturas/CP-089a_sin_integracion_mensaje_claro.png
A58: CP-112 | B58: RF-VTA-04 | C58: Un error del CRM se muestra y queda registrado | D58: Credenciales del CRM vencidas | E58: Enviar una propuesta con credenciales vencidas. | F58: El usuario recibe un mensaje de autenticación fallida (401) y la propuesta no queda como sincronizada. | G58: Resiliencia | H58: Integración | I58: Alta | J58: R-08 | K58: Sí | L58: Aprobado | M58: 46317 | O58: Ejecución 22-10: HubSpot: 401 «API key inválida o sin permisos»; Salesforce: 401 «Consumer Key/Secret inválidos o sin permisos»; no queda «synced» y no se crea nada en el CRM. Si ya estaba sincronizada, conserva sus IDs. 7/7 verificaciones. (Que el 401 no se registre es D-001, evaluado en CP-019.) Pantalla: aviso «API key inválida o sin permisos». La sesión se conserva y no se intenta renovar (/auth/refresh) por un 401 del CRM. CRM REAL: HubSpot rechaza la clave inválida → 401 y propuesta «failed» (3/3). Salesforce real: 401 «Consumer Key/Secret inválidos» en 1 a 2 s en 3 de 7 corridas, pero en las otras 4 el endpoint de token tardó más de 8 s y la app respondió 504 y registró el fallo (L-09, causa externa). [22-10-2026; API · script · emulador · pantalla · CRM real] Evidencia automática revisada: backend/tests/test_proposals_crm.py cubre el 401. | P58: Captura y reporte | Q58: Aviso «API key inválida o sin permisos» con la sesión conservada. | R58: Script Python (httpx) + Chrome (CDP) + CRM real | S58: Automatizada | T58: Evidencia/Scripts/run_rfvta04_api.py; Evidencia/Scripts/run_rfvta04_real.py; backend/tests/test_proposals_crm.py | U58: Evidencia/Salidas_de_scripts/CP-112_credenciales_vencidas_22-oct.txt; Evidencia/Capturas/CP-112a_credenciales_vencidas_aviso_401.png; Evidencia/Salidas_de_scripts/CP-112_REAL_CRM_22-oct.txt; Evidencia/Salidas_de_scripts/CP-112_Salesforce_REAL_CRM_22-oct.txt; Evidencia/Salidas_de_scripts/CP-112_Salesforce_intermitencia_22-oct.txt
A59: CP-113 | B59: RF-VTA-04 | C59: Un error del CRM se muestra y queda registrado | D59: Tiempo agotado del CRM | E59: Enviar una propuesta simulando que el CRM no responde. | F59: El usuario recibe un mensaje de tiempo agotado (504) y puede reintentar. | G59: Resiliencia | H59: Integración | I59: Alta | J59: R-08 | K59: Sí | L59: Aprobado | M59: 46317 | N59: RF04-D-001 | O59: Ejecución 22-10: HubSpot y Salesforce: 504 «Timeout al conectar con …» en ~2 s; no queda «synced»; el reintento con el CRM disponible responde 200 y «synced». 6/6 del caso. El tiempo agotado ahora también queda registrado en crmSync (8/8 verificaciones; antes no, D-001). El límite real de 8 s no se esperó. Pantalla: aviso «Timeout al conectar con HubSpot» (visible tras corregir D-005; antes quedaba tapado por «Server error»). [22-10-2026; API · script · emulador · pantalla] | P59: Captura y reporte | Q59: Aviso «Timeout al conectar con HubSpot» sin el aviso genérico «Server error». | R59: Script Python (httpx) + Chrome (CDP) | S59: Automatizada | T59: Evidencia/Scripts/run_rfvta04_api.py; backend/tests/test_proposals_crm.py | U59: Evidencia/Salidas_de_scripts/CP-113_tiempo_agotado_22-oct.txt; Evidencia/Capturas/CP-113a_tiempo_agotado_aviso_504.png
A60: CP-114 | B60: RF-VTA-04 | C60: Un error del CRM se muestra y queda registrado | D60: Error del proveedor registrado en la propuesta | E60: Enviar una propuesta simulando un error 5xx del CRM. | F60: El usuario recibe el error (502) y la propuesta queda marcada como fallida con el detalle del error. | G60: Resiliencia | H60: Integración | I60: Alta | J60: R-08 | K60: Sí | L60: Aprobado | M60: 46317 | O60: Ejecución 22-10: Ambos: 502 con el detalle («… error 500 …»); crmSync = {status «failed», error, provider, syncedAt}. 6/6 verificaciones. Pantalla: aviso «HubSpot respondió con error 500: Internal error (simulado)» completo. [22-10-2026; API · script · emulador · pantalla] | P60: Captura y reporte | Q60: Aviso «HubSpot respondió con error 500…» completo. | R60: Script Python (httpx) + Chrome (CDP) | S60: Automatizada | T60: Evidencia/Scripts/run_rfvta04_api.py; backend/tests/test_proposals_crm.py | U60: Evidencia/Salidas_de_scripts/CP-114_error_5xx_registrado_22-oct.txt; Evidencia/Archivos_generados/CP-114_crmSync_fallido.json; Evidencia/Capturas/CP-114a_error_5xx_aviso_con_detalle.png
A61: CP-115 | B61: RF-VTA-04 | C61: Reenviar actualiza y no duplica | D61: Reenvío tras un fallo | E61: Después del caso anterior, corregir la causa y reenviar la misma propuesta. | F61: La propuesta queda sincronizada y el CRM tiene un solo contacto y un solo negocio. | G61: Funcional | H61: Integración | I61: Alta | J61: R-08 | K61: Parcial | L61: Aprobado | M61: 46317 | N61: RF04-D-003 | O61: Ejecución 22-10: Reprueba tras la corrección: (A) 502 y luego 200, 1 contacto y 1 negocio; (B) fallo parcial: el reenvío actualiza el mismo negocio (1 contacto, 1 negocio); (C) tras un reenvío fallido crmSync conserva el ID y el reenvío no duplica, en HubSpot y Salesforce. 7/7 verificaciones. Antes: 2/7 (D-003; salida en ANTES_de_corregir/). Pantalla: con el CRM caído aviso de error; tras restablecerlo, el reenvío da éxito y el CRM queda con 1 contacto y 1 negocio. [22-10-2026; API · script · emulador · pantalla] | P61: Captura y reporte | Q61: Aviso de error con el CRM caído y envío exitoso tras restablecerlo; un solo contacto y un solo negocio. | R61: Script Python (httpx) + Chrome (CDP) | S61: Automatizada | T61: Evidencia/Scripts/run_rfvta04_api.py; backend/tests/test_proposals_crm.py | U61: Evidencia/Salidas_de_scripts/CP-115_reenvio_tras_fallo_22-oct.txt; Evidencia/Archivos_generados/CP-115_estado_HubSpot_fallo_parcial.json; Evidencia/Archivos_generados/CP-115_estado_hubspot_fallo_en_reenvio.json; Evidencia/Archivos_generados/CP-115_estado_salesforce_fallo_en_reenvio.json; Evidencia/Capturas/CP-115a_reenvio_con_CRM_caido_error.png; Evidencia/Capturas/CP-115b_reenvio_tras_corregir_exitoso.png
A62: CP-116 | B62: RF-VTA-04 | C62: El CRM contiene contacto y negocio con monto | D62: Caracteres especiales y monto vacío | E62: Enviar una propuesta con un cliente con tildes y emoji, y otra sin monto. | F62: Los textos se conservan en el CRM; la propuesta sin monto se envía sin error. | G62: Funcional | H62: Integración | I62: Media | J62: R-08 | K62: Parcial | L62: Aprobado | M62: 46317 | O62: Ejecución 22-10: Textos idénticos en el CRM (también la consulta SOQL con apóstrofe «O'Brien»); reenvío sin duplicar; sin monto: 200 y el negocio sin campo de monto; monto 0: 200. 8/8 verificaciones. CRM REAL (HubSpot): textos con tildes, ñ, emoji y apóstrofe conservados y negocio creado sin monto (3/3). [22-10-2026; API · script · emulador · CRM real] | P62: Reporte de pruebas | Q62: Estado del CRM con los textos con tildes, ñ, apóstrofe y emoji, y negocio sin monto. | R62: Script Python (httpx) + CRM real | S62: Automatizada | T62: Evidencia/Scripts/run_rfvta04_api.py; Evidencia/Scripts/run_rfvta04_real.py; backend/tests/test_proposals_crm.py | U62: Evidencia/Salidas_de_scripts/CP-116_caracteres_especiales_y_monto_vacio_22-oct.txt; Evidencia/Archivos_generados/CP-116_estado_hubspot_caracteres_especiales.json; Evidencia/Archivos_generados/CP-116_estado_salesforce_caracteres_especiales.json; Evidencia/Salidas_de_scripts/CP-116_REAL_CRM_22-oct.txt; Evidencia/Archivos_generados/CP-116_REAL_HubSpot_estado.json
A63: CP-117 | B63: RF-VTA-04 | C63: El CRM contiene contacto y negocio con monto | D63: Las credenciales del CRM no se exponen | E63: Enviar una propuesta y revisar la respuesta de la API y el registro del servidor. | F63: Ni la respuesta ni el registro contienen la clave o el secreto del CRM. | G63: Seguridad | H63: Integración | I63: Alta | J63: R-08 | K63: Sí | L63: Aprobado | M63: 46317 | O63: Ejecución 22-10: 0 filtraciones en las 11 respuestas, en lo guardado (solo Fernet + últimos 4) y en el registro; el CRM sí recibió la clave real (el cifrado es reversible). 4/4 verificaciones. El registro es el de Python en proceso, no la terminal real de uvicorn. [22-10-2026; API · script] | P63: Reporte de pruebas | Q63: Resultado de la revisión de respuestas, documento guardado y registro del servidor sin la clave ni el secreto. | R63: Script Python (httpx) | S63: Automatizada | T63: Evidencia/Scripts/run_rfvta04_api.py; backend/tests/test_settings.py | U63: Evidencia/Salidas_de_scripts/CP-117_credenciales_no_se_exponen_22-oct.txt; Evidencia/Archivos_generados/CP-117_registro_del_servidor.log; Evidencia/Archivos_generados/CP-117_ajustes_guardados_cifrados.json
A64: CP-021 | B64: RF-VTA-05 | C64: Una sola lista de 6 estados | D64: Lista única de estados en toda la aplicación | E64: Revisar los estados en la lista de propuestas, los filtros, el dashboard, los reportes y la API. | F64: Solo existen los 6 estados (códigos borrador, enviada, vista, en_negociacion, firmada y rechazada), con los mismos nombres en todos los lugares. | G64: Funcional | H64: Sistema | I64: Alta | J64: R-12 | K64: Parcial | L64: Aprobado | M64: 46316 | O64: v1.2: se agregan los códigos del campo proposal_status. Decisión del equipo (nota del proyecto, 19-10), pendiente de acordar con Alloxentric y de registrar como D-12. Ejecución 21-10: API: el 422 lista los 6 códigos. Informes, filtro y panel solo muestran los 6 estados. | P64: Captura y reporte | Q64: Lista de propuestas con el filtro de estados abierto, el dashboard y el reporte mostrando solo los 6 estados. | R64: Pytest + Playwright | S64: Pendiente
A65: CP-022 | B65: RF-VTA-05 | C65: Solo transiciones válidas | D65: Transiciones válidas permitidas | E65: Recorrer cada transición permitida: borrador→enviada; enviada→vista, en_negociacion o rechazada; vista→en_negociacion o rechazada; en_negociacion→firmada o rechazada. | F65: Cada transición se acepta y actualiza el campo proposal_status. | G65: Funcional | H65: Unitaria | I65: Alta | J65: R-12 | K65: Sí | L65: Aprobado | M65: 46316 | O65: v1.2: Decisión del equipo (nota del proyecto, 19-10), pendiente de acordar con Alloxentric y de registrar como D-12. v1.3: CP-118 cubre las mismas transiciones por API; este caso se mantiene por la captura del control de estado. Ejecución 21-10: Las 8 transiciones se aceptan y el selector ofrece solo los destinos válidos (capturas CP-022a-d). | P65: Captura y reporte | Q65: Control de estado de una propuesta con las opciones disponibles desde cada estado, antes y después de cambiarlo. | R65: Pytest + Playwright | S65: Pendiente
A66: CP-023 | B66: RF-VTA-05 | C66: Solo transiciones válidas | D66: Transiciones inválidas rechazadas (negativo) | E66: Probar transiciones no permitidas (por ejemplo, borrador→firmada, vista→enviada y desde firmada hacia cualquier estado). | F66: El sistema responde 409 y el estado no se modifica. | G66: Funcional | H66: Unitaria | I66: Alta | J66: R-12 | K66: Sí | L66: Aprobado | M66: 46316 | O66: v1.2: se reemplaza la nota «la tabla debe definirse» por la tabla propuesta. Decisión del equipo (nota del proyecto, 19-10), pendiente de acordar con Alloxentric y de registrar como D-12. v1.3: cubierto también por CP-118 (parametrizado); se mantiene por los ejemplos explícitos. Ejecución 21-10: Las transiciones no permitidas (incluidas las desde firmada y origen = destino) dan 409 sin cambiar el estado. | P66: Reporte de pruebas | Q66: — | R66: Pytest | S66: Pendiente
A67: CP-025 | B67: RF-VTA-05 | C67: Cada cambio queda en auditoría | D67: Cambio de estado registrado en auditoría | E67: Cambiar el estado de una propuesta y consultar el registro de auditoría. | F67: Queda un registro de acción proposal_status_changed con usuario, fecha e IP. | G67: Seguridad | H67: Integración | I67: Alta | J67: R-12 | K67: Sí | L67: Aprobado | M67: 46316 | N67: RF05-D-001 | O67: v1.2: se agrega el nombre de la acción de auditoría. Ejecución 21-10: El registro tiene usuario, fecha e IP (más dueño, estado previo y nuevo). Visible en Audit Logs (CP-193b). Ver RF05-D-001. | P67: Captura y reporte | Q67: Pantalla de auditoría con el registro proposal_status_changed del cambio realizado. | R67: Pytest + Playwright | S67: Pendiente
A68: CP-026 | B68: RF-VTA-05 | C68: El cambio de estado no modifica el score | D68: Score no cambia al cambiar de estado | E68: Anotar el score de la oportunidad y el relevance_score del lead, cambiar el estado de la propuesta y volver a consultarlos. | F68: Ninguno de los dos cambia; el estado de la propuesta ya no genera ni modifica un score. | G68: Funcional | H68: Unitaria | I68: Alta | J68: R-12 | K68: Sí | L68: Aprobado | M68: 46316 | O68: v1.2: el score por estado se eliminó (nota del proyecto, 19-10); actualiza D-02. El Agente 1 usa el relevance_score del lead. Ejecución 21-10: Score de la oportunidad: 30 antes y después de 6 cambios de estado, sin escrituras. Lo relativo al relevance_score del lead está en el informe de evidencia. | P68: Reporte de pruebas | Q68: — | R68: Pytest | S68: Pendiente
A69: CP-027 | B69: RF-VTA-05 | C69: Estado Vista (D-01) | D69: Estado Vista se marca manualmente | E69: Marcar manualmente una propuesta en estado enviada como vista (el sistema no detecta la apertura por sí solo). | F69: El estado cambia a vista y queda registrado en auditoría. | G69: Funcional | H69: Integración | I69: Alta | J69: R-12 | K69: Sí | L69: Aprobado | M69: 46316 | O69: Ejecución 21-10: enviada → vista se marca a mano y queda auditado. | P69: Captura y reporte | Q69: Propuesta en estado vista tras marcarla manualmente. | R69: Pytest + Playwright | S69: Pendiente
A70: CP-118 | B70: RF-VTA-05 | C70: Solo transiciones válidas | D70: Las 36 combinaciones de transición (parametrizado) | E70: Una prueba parametrizada intenta cada par de estado origen y destino (6 × 6 = 36), con un usuario que no es admin. | F70: Solo se aceptan las 8 transiciones del flujo. La reapertura rechazada→en_negociacion responde 403 para un usuario que no es admin (se cubre además en CP-185 y CP-186). Las otras 27 combinaciones responden 409 y no cambian el estado. | G70: Funcional | H70: Unitaria | I70: Alta | J70: R-12 | K70: Sí | L70: Aprobado | M70: 46316 | O70: Reemplaza la revisión manual de CP-022 y CP-023. v1.2: las 8 transiciones salen de la nota del proyecto. Decisión del equipo (nota del proyecto, 19-10), pendiente de acordar con Alloxentric y de registrar como D-12. Por confirmar: qué ocurre al pasar al mismo estado (origen = destino). v1.3: corregido el conteo: 36 = 8 válidas + 1 con 403 + 27 con 409. Sigue por decidir qué ocurre cuando origen = destino (6 de las 27). Ejecución 21-10: Probado con usuario no admin: 8 dan 200, 1 da 403 y 27 dan 409. Origen = destino da 409. v1.4: origen = destino queda decidido: responde 409 (verificado el 21-10); ya no está por confirmar. | P70: Reporte de pruebas | Q70: — | R70: Pytest | S70: Pendiente
A71: CP-119 | B71: RF-VTA-05 | C71: Una sola lista de 6 estados | D71: Estado inicial al crear | E71: Crear una propuesta nueva. | F71: La propuesta queda en Borrador. | G71: Funcional | H71: Unitaria | I71: Alta | J71: R-12 | K71: Sí | L71: Aprobado | M71: 46316 | O71: Ejecución 21-10: Nace en borrador aunque se envíe firmada (API, Firestore y pantalla). | P71: Captura y reporte | Q71: Propuesta recién creada mostrando el estado borrador. | R71: Pytest + Playwright | S71: Pendiente
A72: CP-120 | B72: RF-VTA-05 | C72: RNF-01: cada usuario accede solo a sus propios datos | D72: Quién puede cambiar el estado | E72: Con un usuario que no es dueño de la propuesta, intentar cambiar su estado. | F72: El sistema rechaza el cambio (403) y el estado no se modifica. | G72: Seguridad | H72: Integración | I72: Alta | J72: R-12 | K72: Sí | L72: Aprobado | M72: 46316 | O72: v1.3: criterio corregido (era «Solo transiciones válidas»). Confirmar que el backend valide que el usuario es dueño de la propuesta; la nota del proyecto solo confirma el 403 de la reapertura sin admin. Ejecución 21-10: Un usuario que no es dueño ni admin recibe 403 sin cambio y sin auditoría. | P72: Reporte de pruebas | Q72: — | R72: Pytest | S72: Pendiente
A73: CP-121 | B73: RF-VTA-05 | C73: Una sola lista de 6 estados | D73: Nombres antiguos de estado (negativo) | E73: Por API, enviar «Generada» y «accepted» como nuevo estado. | F73: Ambos se rechazan con 422 y un mensaje que lista los estados válidos. | G73: Funcional | H73: Integración | I73: Alta | J73: R-12 | K73: Sí | L73: Aprobado | M73: 46316 | O73: v1.2: se agrega el código 422 (destino inválido) de la nota del proyecto. v1.3: confirmar que el 422 incluya la lista de estados válidos. Ejecución 21-10: «Generada» y «accepted» dan 422 con la lista de estados válidos. v1.4: «accepted» no es un valor de proposal_status: viene del campo status (ciclo de generación). El código lo rechaza igual con 422. | P73: Reporte de pruebas | Q73: — | R73: Pytest | S73: Pendiente
A74: CP-028 | B74: RF-VTA-06 | C74: Marcar Firmada adjuntando documento | D74: Marcar Firmada con documento firmado | E74: Abrir una propuesta En negociación, adjuntar el documento firmado y marcarla Firmada. | F74: La propuesta queda Firmada con el documento adjunto. | G74: Funcional | H74: Integración | I74: Media | J74: — | K74: Sí | L74: Pendiente
A75: CP-029 | B75: RF-VTA-06 | C75: Marcar Firmada adjuntando documento | D75: Marcar Firmada sin documento (negativo) | E75: Intentar marcar Firmada sin adjuntar documento. | F75: El sistema pide el documento y no cambia el estado (interpretación del criterio; confirmar con Alloxentric). | G75: Funcional | H75: Integración | I75: Media | J75: — | K75: Sí | L75: Pendiente
A76: CP-123 | B76: RF-VTA-06 | C76: Marcar Firmada adjuntando el documento | D76: Tipo y tamaño del adjunto (negativo) | E76: Adjuntar un PDF válido, un .exe y un archivo que supera el tamaño máximo. | F76: Se acepta el PDF; el .exe y el archivo grande se rechazan con un mensaje claro. | G76: Funcional | H76: Integración | I76: Media | J76: — | K76: Sí | L76: Pendiente | O76: El tamaño máximo debe definirse.
A77: CP-124 | B77: RF-VTA-06 | C77: Marcar Firmada adjuntando el documento | D77: Archivo con extensión engañosa (seguridad) | E77: Adjuntar un ejecutable renombrado como .pdf. | F77: El sistema lo rechaza al verificar el contenido, no solo la extensión. | G77: Seguridad | H77: Integración | I77: Media | J77: — | K77: Sí | L77: Pendiente
A78: CP-125 | B78: RF-VTA-06 | C78: Marcar Firmada adjuntando el documento | D78: Descargar el documento firmado | E78: Descargar el adjunto de una propuesta Firmada y comparar con el original. | F78: El archivo descargado es idéntico al adjuntado. | G78: Funcional | H78: Integración | I78: Media | J78: — | K78: Sí | L78: Pendiente
A79: CP-126 | B79: RF-VTA-06 | C79: Marcar Firmada adjuntando el documento | D79: Permisos sobre el adjunto | E79: Con otro usuario, intentar adjuntar y descargar el documento de una propuesta ajena. | F79: Ambas acciones se rechazan (403). | G79: Seguridad | H79: Integración | I79: Media | J79: — | K79: Sí | L79: Pendiente
A80: CP-030 | B80: RF-VTA-07 | C80: Crear, editar y eliminar plantillas con variables | D80: Mantener plantillas | E80: Crear una plantilla con variables {variable}, editarla y eliminarla. | F80: Cada operación se guarda; la plantilla eliminada deja de aparecer. | G80: Funcional | H80: Integración | I80: Media | J80: R-09 | K80: Sí | L80: Pendiente
A81: CP-031 | B81: RF-VTA-07 | C81: Variables se completan con datos | D81: Aplicar plantilla completa las variables | E81: Aplicar una plantilla a una propuesta con cliente y datos cargados. | F81: Las variables se reemplazan por los datos del cliente y de la propuesta. | G81: Funcional | H81: Unitaria | I81: Media | J81: R-09 | K81: Sí | L81: Pendiente
A82: CP-032 | B82: RF-VTA-07 | C82: Variables se completan con datos | D82: Variable sin dato disponible (negativo) | E82: Aplicar una plantilla cuya variable no tiene dato en el cliente. | F82: El sistema marca el campo como pendiente de completar y lo señala al usuario; no queda texto con la variable sin aviso. | G82: Funcional | H82: Unitaria | I82: Media | J82: R-09 | K82: Sí | L82: Pendiente
A83: CP-033 | B83: RF-VTA-07 | C83: Clasificar y filtrar por servicio o industria | D83: Clasificación y filtros | E83: Asignar tipo de servicio o industria a plantillas y filtrar por cada uno. | F83: El filtro muestra solo las plantillas que corresponden. | G83: Funcional | H83: Integración | I83: Media | J83: R-09 | K83: Sí | L83: Pendiente
A84: CP-034 | B84: RF-VTA-07 | C84: Bloque editable de condiciones comerciales | D84: Condiciones comerciales en toda plantilla | E84: Crear una plantilla nueva y abrir las existentes. | F84: Todas incluyen un bloque editable de condiciones comerciales. | G84: Funcional | H84: Integración | I84: Media | J84: R-09 | K84: Sí | L84: Pendiente
A85: CP-127 | B85: RF-VTA-07 | C85: Las variables se completan con datos | D85: Llaves no válidas en el texto | E85: Aplicar una plantilla que contiene {cliente}, {{x}} y {a b}. | F85: {cliente} se reemplaza; las llaves no válidas se conservan tal cual y no hay error. | G85: Funcional | H85: Unitaria | I85: Media | J85: R-09 | K85: Sí | L85: Pendiente | O85: Posible evidencia: tests/test_templates.py (por revisar).
A86: CP-128 | B86: RF-VTA-07 | C86: Las variables se completan con datos | D86: Variable repetida | E86: Aplicar una plantilla en la que {cliente} aparece tres veces. | F86: Las tres apariciones se reemplazan. | G86: Funcional | H86: Unitaria | I86: Media | J86: R-09 | K86: Sí | L86: Pendiente
A87: CP-129 | B87: RF-VTA-07 | C87: Crear, editar y eliminar plantillas con variables | D87: Plantilla de otro usuario (seguridad) | E87: Con el usuario B, editar, eliminar y aplicar una plantilla privada del usuario A. | F87: Las tres acciones se rechazan (403). | G87: Seguridad | H87: Integración | I87: Alta | J87: R-09 | K87: Sí | L87: Pendiente
A88: CP-130 | B88: RF-VTA-07 | C88: Crear, editar y eliminar plantillas con variables | D88: Extracción de variables desde un archivo | E88: Subir un Word con variables {nombre} y {monto}, y un archivo inválido. | F88: Del Word se extraen las dos variables; el archivo inválido se rechaza con un mensaje. | G88: Funcional | H88: Integración | I88: Media | J88: R-09 | K88: Parcial | L88: Pendiente
A89: CP-131 | B89: RF-VTA-07 | C89: Crear, editar y eliminar plantillas con variables | D89: Contenido demasiado largo (negativo) | E89: Guardar una plantilla de 1 MB de texto. | F89: El sistema la rechaza e indica el límite de tamaño. | G89: Funcional | H89: Integración | I89: Baja | J89: R-09 | K89: Sí | L89: Pendiente | O89: El límite debe definirse.
A90: RF08-CP-01 | B90: RF-VTA-08 | C90: El vendedor obtiene un borrador editable del material solicitado | D90: Generar un caso de éxito | E90: Precondición: Los 3 documentos de ejemplo cargados. Sales enablement → «Caso de éxito» → tema «Cobranza telefónica para cartera morosa de retail» → Generar borrador. | F90: El botón muestra «Generando…». Luego se abre el borrador con título, Cliente y contexto, Desafío, Solución y Resultados; aparece en «Borradores guardados»; en «Fuentes usadas» figura Propuesta_BPO_Cobranza_Retail_Mercantil.docx. | G90: Funcional | H90: Sistema | I90: Alta | J90: — | K90: No | L90: Aprobado | M90: 46309 | O90: Origen: CP-01 del plan de RF-VTA-08 (CU-01). Obtenido: Caso de éxito con estructura y fuente correctas.
A91: RF08-CP-02 | B91: RF-VTA-08 | C91: El borrador se basa en información cargada y no presenta como reales datos inexistentes | D91: Cifras y nombres trazables a las fuentes | E91: Precondición: Borrador de CP-01. Revisar cada cifra, nombre y afirmación del borrador contra la tabla de hechos verificables (sección 6). | F91: Toda cifra y nombre está en las fuentes. Los resultados obtenidos (que las fuentes no contienen) aparecen como [COMPLETAR: …] y el contador «Partes por completar» es mayor que 0. Cero certificaciones o clientes inventados. | G91: Funcional | H91: Sistema | I91: Alta | J91: — | K91: No | L91: Aprobado | M91: 46309 | N91: RF08-D-001 | O91: Origen: CP-02 del plan de RF-VTA-08 (CU-01). Obtenido: Cifras trazables; resultados como [COMPLETAR]. Marcadores en inglés corregidos (D-001).
A92: RF08-CP-03 | B92: RF-VTA-08 | C92: El vendedor obtiene un borrador editable del material solicitado; El borrador se basa en información cargada y no presenta como reales datos inexistentes | D92: Generar una comparativa | E92: Precondición: Documentos de ejemplo. «Comparativa» → tema «Contact center externo omnicanal vs. equipo interno» → Generar. | F92: Borrador con criterios comparados. Los datos del equipo interno (que no están en las fuentes) quedan como [COMPLETAR] o en «Puntos por validar»; no hay precios ni cifras de terceros inventados. | G92: Funcional | H92: Sistema | I92: Alta | J92: — | K92: No | L92: Aprobado | M92: 46312 | N92: RF08-D-004, RF08-D-005 | O92: Origen: CP-03 del plan de RF-VTA-08 (CU-02). Obtenido: Reprueba (17-oct): títulos en español, marcadores [COMPLETAR] en español (20), citas solo en Evidencia y cifras de la propuesta introducidas como «en una propuesta anterior» con nota de que no son estándar; sin datos inventados del equipo interno. Observación: «Cuándo conviene» usa condiciones de esa propuesta como criterio general (mejora posible, no bloqueante).
A93: RF08-CP-04 | B93: RF-VTA-08 | C93: El vendedor obtiene un borrador editable del material solicitado; El borrador se basa en información cargada y no presenta como reales datos inexistentes | D93: Respuesta a objeción de precio | E93: Precondición: Documentos de ejemplo. «Respuesta a objeción» → «El precio del contact center es mayor al de nuestro proveedor actual» → Generar. | F93: Borrador con objeción replanteada, qué hay detrás, respuesta sugerida, evidencia citada de las fuentes y pregunta de seguimiento. No promete descuentos ni resultados no respaldados. | G93: Funcional | H93: Sistema | I93: Alta | J93: — | K93: No | L93: Aprobado | M93: 46309 | N93: RF08-D-002 | O93: Origen: CP-04 del plan de RF-VTA-08 (CU-03). Obtenido: Objeción de precio sin inventar. La respuesta nombraba a otro cliente (D-002); corregido.
A94: RF08-CP-05 | B94: RF-VTA-08 | C94: El borrador se basa en información cargada y no presenta como reales datos inexistentes | D94: Objeción corta sin palabras en común con los documentos | E94: Precondición: Documentos de ejemplo. «Respuesta a objeción» → «Es muy caro» → Generar. | F94: Resultado esperado documentado (riesgo R-01): o bien 422 con el aviso de falta de información, o bien un borrador respaldado. Anotar cuál ocurre; si el equipo decide que debe generar, se devuelve a iterar. | G94: Funcional | H94: Sistema | I94: Media | J94: — | K94: No | L94: Aprobado | M94: 46309 | O94: Origen: CP-05 del plan de RF-VTA-08 (CU-03). Obtenido: Resultado correcto según el tester.
A95: RF08-CP-06 | B95: RF-VTA-08 | C95: El vendedor obtiene un borrador editable del material solicitado | D95: Cliente tomado de la oportunidad | E95: Precondición: Oportunidad «Financiera Horizonte» creada. Elegir esa oportunidad en el selector, dejar «Cliente» vacío, tipo «Caso de éxito», tema «Cobranza», Generar. | F95: El borrador queda con cliente «Financiera Horizonte» (visible en la lista) y la generación considera ese cliente. | G95: Funcional | H95: Sistema | I95: Media | J95: — | K95: No | L95: Aprobado | M95: 46312 | O95: Origen: CP-06 del plan de RF-VTA-08 (CU-01). Obtenido: 17-oct: el borrador queda con título y cliente «Financiera Horizonte»; nada inventado (8 [COMPLETAR], figuras de otra propuesta presentadas como tales y sin nombrar al cliente). Observación: no usa los datos de la oportunidad (12.000 morosos, 9 %); queda como decisión P-6.
A96: RF08-CP-07 | B96: RF-VTA-08 | C96: El vendedor obtiene un borrador editable del material solicitado | D96: Cliente escrito a mano | E96: Precondición: Documentos de ejemplo. Sin oportunidad, escribir «Banco Andino» en Cliente, tema «Contact center», Generar. | F96: El borrador se guarda con cliente «Banco Andino»; la lista lo muestra. | G96: Funcional | H96: Sistema | I96: Baja | J96: — | K96: No | L96: Aprobado | M96: 46312 | O96: Origen: CP-07 del plan de RF-VTA-08 (CU-01). Obtenido: 17-oct: el borrador se guarda para «Banco Andino» (título y texto). Distingue propuesta de implementación, separa objetivos de resultados y deja 8 [COMPLETAR]. Observaciones menores: títulos de sección con «:» final, sección Evidencia reducida a una sola cita y datos repetidos (40 agentes).
A97: RF08-CP-08 | B97: RF-VTA-08 | C97: El vendedor obtiene un borrador editable del material solicitado | D97: Idiomas English y Português | E97: Precondición: Documentos de ejemplo. Generar el mismo caso de éxito con idioma English y luego Português. | F97: Títulos de sección y texto en el idioma elegido; las citas de fuente conservan el título original del documento. | G97: Funcional | H97: Sistema | I97: Media | J97: — | K97: Sí | L97: Aprobado | M97: 46312 | O97: Origen: CP-08 del plan de RF-VTA-08 (CU-01). Obtenido: Automatizado 17-oct: en English y Português los títulos salen en el idioma elegido, sin títulos en español; la cita conserva el nombre original del documento (5 y 6 [COMPLETAR]).
A98: RF08-CP-09 | B98: RF-VTA-08 | C98: El vendedor obtiene un borrador editable del material solicitado | D98: Instrucción adicional de tono y extensión | E98: Precondición: Documentos de ejemplo. Instrucción adicional: «Tono formal, máximo 150 palabras». Generar. | F98: El borrador respeta razonablemente el tono y la extensión, sin romper la estructura ni las reglas de fuentes. | G98: Funcional | H98: Sistema | I98: Baja | J98: — | K98: Sí | L98: Aprobado | M98: 46312 | O98: Origen: CP-09 del plan de RF-VTA-08 (CU-01). Obtenido: Automatizado 17-oct: 105 palabras (límite 150) con la estructura intacta. El tono no se evaluó de forma automática.
A99: RF08-CP-10 | B99: RF-VTA-08 | C99: El borrador se basa en información cargada y no presenta como reales datos inexistentes | D99: Usuario sin documentos cargados | E99: Precondición: Usuario sin documentos cargados (usuario nuevo). Generar cualquier caso de éxito. | F99: Aviso «No hay información cargada que respalde este material…». No se crea borrador. En el log del backend no hay llamada al modelo para esa solicitud. | G99: Funcional | H99: Sistema | I99: Alta | J99: — | K99: No | L99: Aprobado | M99: 46309 | O99: Origen: CP-10 del plan de RF-VTA-08 (CU-01). Obtenido: Aviso de falta de información; sin borrador.
A100: RF08-CP-11 | B100: RF-VTA-08 | C100: El borrador se basa en información cargada y no presenta como reales datos inexistentes | D100: Tema sin relación con los documentos | E100: Precondición: Documentos de ejemplo. Tema «Receta de cocina vegana con harina de garbanzo» → Generar. | F100: Responde 422 y muestra el aviso; no se crea borrador ni se inventa contenido. | G100: Funcional | H100: Sistema | I100: Alta | J100: — | K100: No | L100: Aprobado | M100: 46309 | O100: Origen: CP-11 del plan de RF-VTA-08 (CU-01). Obtenido: 422 con aviso; sin borrador.
A101: RF08-CP-12 | B101: RF-VTA-08 | C101: El borrador se basa en información cargada y no presenta como reales datos inexistentes | D101: Documento eliminado deja de influir | E101: Precondición: Un solo documento cargado (Cobranza Mercantil). Generar «Cobranza» (funciona) → borrar el documento en Configuración → Propuestas históricas → generar el mismo tema. | F101: Después de borrar el documento ya no se puede generar (aviso de falta de información): los fragmentos se eliminaron. | G101: Funcional | H101: Sistema | I101: Media | J101: — | K101: Sí | L101: Aprobado | M101: 46312 | O101: Origen: CP-12 del plan de RF-VTA-08 (CU-01). Obtenido: Automatizado 17-oct, con un documento de prueba propio: antes de borrarlo genera (201); tras borrarlo (204) la misma generación responde 422 «sin información».
A102: RF08-CP-13 | B102: RF-VTA-08 | C102: El vendedor obtiene un borrador editable del material solicitado | D102: Editar y guardar el borrador | E102: Precondición: Un borrador existente. Abrirlo, comprobar que «Guardar cambios» está deshabilitado, cambiar una frase, pulsar Guardar, recargar la página y abrirlo de nuevo. | F102: El botón se habilita solo con cambios; aparece «Borrador guardado»; tras recargar el texto editado persiste. | G102: Funcional | H102: Sistema | I102: Alta | J102: — | K102: No | L102: Aprobado | M102: 46309 | O102: Origen: CP-13 del plan de RF-VTA-08 (CU-04). Obtenido: Guarda y persiste tras recargar.
A103: RF08-CP-14 | B103: RF-VTA-08 | C103: El vendedor obtiene un borrador editable del material solicitado | D103: No se guarda un borrador vacío | E103: Precondición: Un borrador abierto. Borrar todo el texto del editor. | F103: «Guardar cambios» permanece deshabilitado; no se puede guardar un borrador vacío. | G103: Funcional | H103: Sistema | I103: Media | J103: — | K103: Sí | L103: Aprobado | M103: 46312 | O103: Origen: CP-14 del plan de RF-VTA-08 (CU-04). Obtenido: Automatizado en la app real 17-oct: con el texto vacío «Guardar cambios» queda deshabilitado.
A104: RF08-CP-15 | B104: RF-VTA-08 | C104: El vendedor obtiene un borrador editable del material solicitado | D104: Copiar al portapapeles | E104: Precondición: Un borrador abierto. Pulsar «Copiar» y pegar en un editor de texto. | F104: Aviso «Copiado» y el texto pegado coincide con el editor (incluidos los cambios sin guardar). | G104: Funcional | H104: Sistema | I104: Baja | J104: — | K104: Sí | L104: Aprobado | M104: 46312 | O104: Origen: CP-15 del plan de RF-VTA-08 (CU-04). Obtenido: Automatizado en la app real 17-oct: aviso «Copiado» y el portapapeles coincide con el editor, incluidos los cambios sin guardar.
A105: RF08-CP-16 | B105: RF-VTA-08 | C105: El vendedor obtiene un borrador editable del material solicitado | D105: Lista de borradores | E105: Precondición: Al menos 3 borradores de distinto tipo. Abrir Sales enablement y observar la lista. | F105: Orden del más reciente al más antiguo; cada fila muestra tipo, título, cliente, tema y fecha; al pulsar una fila se abre en el editor. | G105: Funcional | H105: Sistema | I105: Media | J105: — | K105: Sí | L105: Aprobado | M105: 46312 | O105: Origen: CP-16 del plan de RF-VTA-08 (CU-05). Obtenido: Automatizado 17-oct: 10 borradores en orden descendente con tipo, título, cliente, tema y fecha; revisado en captura.
... A120: RF08-CP-31 | B120: RF-VTA-08 | C120: El vendedor obtiene un borrador editable del material solicitado | D120: Cambiar de sección durante la generación | E120: Precondición: Documentos de ejemplo. Generar y, sin esperar, ir a otra sección; volver a Sales enablement tras unos segundos. | F120: El borrador generado aparece en la lista (se guarda en el servidor aunque se cambie de página). | G120: Resiliencia | H120: Sistema | I120: Media | J120: — | K120: Sí | L120: Aprobado | M120: 46312 | O120: Origen: CP-31 del plan de RF-VTA-08 (CU-01). Obtenido: Automatizado 17-oct: al cambiar de sección durante la generación, el borrador aparece en la lista al volver; también se guarda si el cliente corta la conexión.
A121: RF08-CP-32 | B121: RF-VTA-08 | C121: El vendedor obtiene un borrador editable del material solicitado | D121: Temas visuales y ancho de celular | E121: Abrir la página en tema Claro, Oscuro y Noon y en ancho de celular (≈390 px). | F121: Texto legible en los tres temas, sin elementos cortados ni scroll horizontal en la página. | G121: Funcional | H121: Sistema | I121: Baja | J121: — | K121: Sí | L121: Aprobado | M121: 46312 | N121: RF08-D-006 | O121: Origen: CP-32 del plan de RF-VTA-08 (CU-05). Obtenido: Automatizado 17-oct: sin desborde horizontal en Claro, Oscuro y Noon, en 1440 px y 390 px. Las capturas revelaron un contraste insuficiente del selector de tipo en tema oscuro (D-006); corregido y verificado.
A122: RF08-CP-33 | B122: RF-VTA-08 | C122: El vendedor obtiene un borrador editable del material solicitado | D122: Idiomas de la interfaz | E122: Cambiar el idioma de la interfaz a Español, English y Português. | F122: Todos los textos de la página están traducidos; no aparecen claves como «enablement.title». | G122: Funcional | H122: Sistema | I122: Baja | J122: — | K122: Sí | L122: Aprobado | M122: 46312 | O122: Origen: CP-33 del plan de RF-VTA-08 (CU-05). Obtenido: Automatizado 17-oct: en Español, English y Português el título se traduce y no aparecen claves sin traducir.
A123: RF08-CP-35 | B123: RF-VTA-08 | C123: El borrador se basa en información cargada y no presenta como reales datos inexistentes | D123: No nombrar a otros clientes en la respuesta sugerida | E123: Precondición: Documentos de ejemplo; cliente del campo «Cliente» distinto de los de las fuentes (por ejemplo «Acme»). Generar una respuesta a objeción o un caso de éxito escribiendo «Acme» en Cliente. | F123: El cuerpo del borrador y la respuesta sugerida (lo que se diría al prospecto) no nombran a Banco Andino, Retail Mercantil ni Seguros del Pacífico; los describen de forma genérica («un banco»). Los nombres solo pueden aparecer en las citas «(Fuente: …)», que son de uso interno. En una objeción, la «Respuesta sugerida» (lo que se diría al prospecto) no lleva citas ni dotación, SLAs, penalidades o precios de otro cliente; habla de capacidades generales y hace preguntas. | G123: Seguridad | H123: Sistema | I123: Alta | J123: — | K123: No | L123: Aprobado | M123: 46309 | N123: RF08-D-002, RF08-D-003 | O123: Origen: CP-35 del plan de RF-VTA-08 (CU-03). Obtenido: Tras D-002 y D-003 la respuesta sugerida no nombra clientes ni lleva citas ni condiciones de otro cliente.
A124: RF08-CP-36 | B124: RF-VTA-08 | C124: El vendedor obtiene un borrador editable del material solicitado | D124: Descargar el borrador en Word | E124: Precondición: Un borrador abierto en el editor. Escribir una línea nueva en el editor sin guardar y pulsar «Descargar Word». | F124: Se descarga un archivo .docx con el título, los títulos de sección como encabezados y el texto que se ve en el editor (incluida la línea sin guardar). El borrador guardado no cambia. Otro usuario o sin sesión no puede descargarlo (403) y un id inexistente da 404. | G124: Funcional | H124: Sistema | I124: Media | J124: — | K124: Sí | L124: Aprobado | M124: 46312 | N124: RF08-D-007 | O124: Origen: CP-36 del plan de RF-VTA-08 (CU-04). Obtenido: Automatizado 17-oct (API y navegador): el Word trae 5 encabezados y el texto editado sin guardar; el guardado no cambia; otro usuario y sin token dan 403, id inexistente 404. En la app real el botón descarga un .docx de unos 37 KB con el texto sin guardar. La prueba de interfaz detectó que el botón no estaba en la pantalla (D-007); corregido.
...

Sheet Hitos
A1: Pruebas por hito y criterio de salida
A2: Fechas y criterios de salida: PMBOK v2. La columna «Pruebas previstas» es propuesta de QA alineada con los entregables de cada hito.
A4: Hito | B4: Fecha | C4: Criterio de salida (PMBOK v2) | D4: Aprueba | E4: Pruebas previstas (propuesta)
A5: Consolidado validado | B5: 16-10-2026 | C5: Consolidado v0.3 revisado; D-04, D-07 y D-10 aprobadas por escrito; acta de validación de criterios. | D5: Alloxentric y NoonDalton | E5: Informado como cumplido por el equipo; falta referenciar el acta de validación firmada.
A6: Procesamiento asíncrono y modelo de datos | B6: 21-10-2026 | C6: Celery y Redis configurados; lista única de estados; catálogo y perfil de cliente en Firestore. | D6: Alloxentric | E6: RNF-06, RF-05, RF-02, RF-03.
A7: Evaluación 2 – Avance | B7: 24-10-2026 | C7: Flujo guiado con catálogo, perfil y estados en staging; Celery/Redis operativo; medición base del tiempo de generación. | D7: Alloxentric | E7: RF-01 (flujo), RNF-03 (medición base). Se recalibran umbrales.
A8: Motor de propuestas completo | B8: 07-11-2026 | C8: Generación con RAG dinámico, plantillas, versiones y exportación PDF/DOCX con diseño corporativo. | D8: Alloxentric | E8: RF-01, 07, 11, 12 y RNF-04.
A9: Pipeline y CRM operativos | B9: 14-11-2026 | C9: Agentes 1 y 3 con Review Queue sin envío automático; integración con CRM probada. | D9: Alloxentric | E9: RF-13, 14, 16 y RF-04.
A10: Congelamiento de funcionalidades | B10: 21-11-2026 | C10: Entregables Must en Listo para Demo; cobertura de 80% o más; 0 defectos críticos abiertos. | D10: Alloxentric | E10: RF-10, 09, 08 y RF-06 (marcar Firmada).
A11: Suite de calidad completa | B11: 25-11-2026 | C11: Cobertura de pruebas, RBAC, auditoría y tratamiento de fallas validados. | D11: Alloxentric | E11: RNF-01, 02, 03, 05.
A12: Evaluación 3 – Producción | B12: 28-11-2026 | C12: Producción con pruebas E2E aprobadas, RBAC y auditoría validados, manual de despliegue; 3 defectos altos o menos. | D12: Alloxentric y NoonDalton | E12: E2E, regresión completa, manual de despliegue.
A13: Aceptación y correcciones | B13: 09-12-2026 | C13: Pruebas de aceptación con Alloxentric y NoonDalton; 100% de defectos críticos y altos corregidos y verificados. | D13: NoonDalton | E13: Aceptación formal; solo se corrigen defectos.
A14: Entrega completa | B14: 14-12-2026 | C14: Software, informe de requerimientos e informe de aseguramiento de calidad entregados. | D14: Alloxentric | E14: Informe de resultados de pruebas.
A15: Cierre y defensa | B15: 19-12-2026 | C15: Aceptación final firmada por NoonDalton. | D15: NoonDalton | E15: —

Sheet Defectos
A1: Defectos registrados
A2: Defectos de RF-VTA-08 ya encontrados y corregidos (plan propio, 14 a 17-10-2026). Nuevos defectos se agregan debajo con el prefijo del módulo.
A4: ID | B4: Caso | C4: Severidad | D4: Descripción y evidencia | E4: Estado | F4: Fecha de reporte
A5: RF01-D-001 | B5: CP-22 / RF01-PA-21 (plan de RF-VTA-01) | C5: Menor | D5: En el cuadro de progreso de la generación aparecía «52% complete» y el botón «Retry» en inglés aunque la interfaz estaba en español. Corregido y reprobado el 20-10-2026 (plan de RF-VTA-01). | E5: Corregido | F5: 20 de octubre de 2026
A6: RF01-D-002 | B6: CP-14 (plan de RF-VTA-01) | C6: Menor | D6: En propuestas en español quedaba la palabra en inglés «Assumption:» en las condiciones comerciales (el prompt traía ese ejemplo en inglés). Corregido y reprobado el 20-10-2026; salida: D-002_reprueba_assumption_en_ingles_20-oct.txt. | E6: Corregido | F6: 20 de octubre de 2026
A7: RF04-D-001 | B7: CP-019 (también CP-113) | C7: Mayor | D7: Los errores 401 (credenciales) y 504 (tiempo agotado) llegan al usuario pero NO quedan registrados en la propuesta: crmSync queda vacío o con el estado anterior. Solo el 502 guarda status «failed» y el detalle (proposals.py:1292-1303). Incumple C3 («se muestra y queda registrado»). Evidencia: CP-019 (a) y CP-113 (complementaria). CORRECCIÓN: los 401 y 504 se registran igual que el 502 (_record_crm_failure en proposals.py). REPRUEBA 22-10-2026: CP-019 y CP-113 pasan; pytest 772/772. Corrección en el código sin commit al 22-10-2026. | E7: Corregido | F7: 22 de octubre de 2026
A8: RF04-D-002 | B8: CP-019 | C8: Mayor | D8: Si el CRM está caído (conexión rechazada o DNS) HubSpotClient/SalesforceClient dejan pasar httpx.ConnectError, que el router no captura (solo atrapa CrmAuthError, CrmTimeoutError y CrmProviderError): la API responde 500 «Internal Server Error» sin mensaje ni registro en la propuesta; el frontend mostrará el texto genérico de axios. Evidencia: CP-019 (b) y (c). CORRECCIÓN: el router captura httpx.HTTPError y responde 502 «No se pudo conectar con HubSpot/Salesforce…», registrado en crmSync. REPRUEBA 22-10-2026: CP-019 (b)(c) pasan. Corrección en el código sin commit al 22-10-2026. | E8: Corregido | F8: 22 de octubre de 2026
A9: RF04-D-003 | B9: CP-115 (también CP-018) | C9: Mayor | D9: Tras un fallo el reenvío duplica en el CRM. Cuando send-to-crm falla con 502, crmSync se sobrescribe con {status failed, error} y se pierde el ID del negocio/oportunidad ya vinculado; además, si el negocio se crea y falla la asociación, su ID nunca se guarda. El siguiente envío crea otro negocio (HubSpot: 2 negocios; Salesforce: 2 oportunidades). Incumple C2. Evidencia: CP-115 (B) y (C) y los JSON de estado. CORRECCIÓN: los fallos conservan los IDs ya vinculados y guardan los creados a medias (crm_service.upsert_deal informa el ID del negocio si falla la asociación). REPRUEBA 22-10-2026: CP-115 A, B y C pasan; antes en ANTES_de_corregir/. Corrección en el código sin commit al 22-10-2026. | E9: Corregido | F9: 22 de octubre de 2026
A10: RF04-D-004 | B10: Complementario (CP-088) | C10: Menor | D10: El router solo comprueba que clientEmail no sea vacío/nulo: un correo de solo espacios o mal formado («no-es-un-correo») se envía al CRM, que lo rechaza, y el usuario recibe un 502 con el texto del proveedor y la propuesta queda «failed». Debería rechazarse con 400 «falta el correo» antes de llamar. Evidencia: CP-088 (complementarias). CORRECCIÓN: el correo se recorta y se valida (400) antes de llamar al CRM. REPRUEBA 22-10-2026: CP-088 pasa 7/7. Corrección en el código sin commit al 22-10-2026. | E10: Corregido | F10: 22 de octubre de 2026
A11: RF04-D-005 | B11: CP-019, CP-113, CP-114 (pantalla) | C11: Menor | D11: En pantalla, los errores 502 y 504 del CRM mostraban dos avisos superpuestos: el específico («No se pudo conectar…», «Timeout…», «HubSpot respondió con error 500…») quedaba tapado o cortado por el aviso genérico «Server error. Please try again.» del interceptor de axios (todo estado ≥ 500). En CP-113 el mensaje del CRM no se veía. Evidencia previa: Capturas/ANTES_de_corregir_D-005/. CORRECCIÓN: la llamada send-to-crm pasa suppressServerErrorToast y el interceptor la respeta (axios.js, proposalsApi.js), con el mismo patrón de suppressPermissionToast. REPRUEBA 22-10-2026: CP-019a, CP-113a, CP-114a y CP-115a muestran solo el mensaje del CRM; vitest 115/115. Corrección en el código sin commit al 22-10-2026. | E11: Corregido | F11: 22 de octubre de 2026
A12: RF04-D-006 | B12: CP-112 (pantalla) | C12: Menor | D12: El 401 que devuelve send-to-crm cuando las credenciales del CRM están vencidas se trata como sesión vencida: el interceptor de axios llama a /auth/refresh (comprobado con una petición a /auth/refresh) y reintenta. Con una sesión válida solo rota los tokens de más y repite la petición; si el refresco fallara, el usuario perdería la sesión por un problema del CRM (en la corrida de QA la sesión se perdió porque el token de renovación era ficticio). CORRECCIÓN: la llamada send-to-crm se marca crmRequest y el interceptor solo renueva la sesión si el 401 trae «Could not validate credentials» o «Not authenticated» (axios.js, proposalsApi.js). REPRUEBA 22-10-2026: con credenciales vencidas la sesión se conserva y no hay petición a /auth/refresh (CP-112a; antes en ANTES_de_corregir_D-006_D-007_D-008/). Corrección en el código sin commit al 22-10-2026. | E12: Corregido | F12: 22 de octubre de 2026
A13: RF04-D-007 | B13: CP-016 (celular 390x844) | C13: Menor | D13: En ancho de celular los botones del pie de la propuesta (Editar, Descargar DOCX, Descargar PDF, Subir al CRM) quedan cortados y «Subir al CRM» se ve a medias. Evidencia: CP-016g y CP-016h. CORRECCIÓN: el pie del modal usa flex-wrap y queda fijo abajo con sticky (ContentLibraryPage.jsx). Primera versión (solo flex-wrap) dejaba el pie fuera de pantalla hasta desplazar el recuadro. REPRUEBA 22-10-2026: en 390x844 los seis botones están visibles sin desplazar (CP-016g, CP-016j); en escritorio el modo de edición conserva su pie («Cancelar», «Guardar cambios»). Corrección en el código sin commit al 22-10-2026. | E13: Corregido | F13: 22 de octubre de 2026
A14: RF04-D-008 | B14: CP-016, CP-088 (pantalla) | C14: Menor | D14: Los textos del flujo CRM no usan las traducciones: el aviso de éxito «Proposal sent to HubSpot/Salesforce.», «Sending...» y el recuadro «Client email required / Save & send» salen en inglés con la interfaz en español o portugués; el recuadro dice «HubSpot needs an email…» aunque el proveedor sea Salesforce; y un correo mal formado muestra «Request failed with status code 422» en vez de explicar el formato. Evidencia: CP-016b, CP-088a y CP-088b. CORRECCIÓN: los textos pasan a las tablas es/en/pt (crmSent, crmSending, crmEmail*), el recuadro ya no nombra a HubSpot, valida el formato del correo antes de guardar y los errores de validación en lista se muestran con su mensaje. REPRUEBA 22-10-2026: CP-016b (es), CP-016i (en), CP-088a y CP-088b traducidos. Corrección en el código sin commit al 22-10-2026. | E14: Corregido | F14: 22 de octubre de 2026
A15: RF05-D-001 | B15: CP-025 (relacionado) | C15: Menor | D15: El filtro por usuario de la pantalla de auditoría (GET /admin/audit-logs?userId=…) responde 500: Firestore exige un índice compuesto (auditLogs: userId, timestamp descendente) que el proyecto no tiene y el endpoint no maneja el error. Sin filtro funciona. Relacionado con la decisión pendiente sobre el filtro de auditoría en admin.py. | E15: Abierto | F15: 21 de octubre de 2026
... A35: RF14-D-003 | B35: CP-054 | C35: Menor | D35: Un aviso sin empresa se guarda igual como lead, y el criterio C1 pide empresa. Falta decidir si debe rechazarse o completarse. Corregido: commit a2ddc49 (22-10-2026). Reprueba: Pasa. | E35: Corregido | F35: 21 de octubre de 2026
